[
  {
    "name": "Gaming Squad Gaming Vans",
    "address": "Gaming Squad House, Barry, CF63 4DG, GB",
    "phone": "01446 327111",
    "international_phone": "01446 327111",
    "website": "https://gamingsquad.co.uk/",
    "google_maps_url": "https://www.google.com/maps/place/Gaming+Squad+Gaming+Vans/data=!4m7!3m6!1s0x486e0542c2c02161:0xc0056f1d426616e!8m2!3d51.4004838!4d-3.2711699!16s%2Fg%2F11f66rnv4h!19sChIJYSHAwkIFbkgRbmEm1PFWAAw?authuser=0&hl=en&rclk=1",
    "rating": 5.0,
    "total_reviews": 148,
    "business_status": "OPERATIONAL",
    "opening_hours": "{}",
    "types": "Children's party service",
    "lat": 51.400484,
    "lng": -3.27117,
    "found_in_location": "Barry",
    "found_with_query": "limo wales"
  },
  {
    "name": "J&K TRAVEL LTD",
    "address": "34 Clarendon Rd, Wallasey, CH44 8EL, GB",
    "phone": "07709 071710",
    "international_phone": "07709 071710",
    "website": "http://jktravelwirral.co.uk/",
    "google_maps_url": "https://www.google.com/maps/place/J%26K+TRAVEL+LTD/data=!4m7!3m6!1s0x487b268a075c3019:0x8e3e9c8a84edecf9!8m2!3d53.4162591!4d-3.0272447!16s%2Fg%2F11gfn9yk6w!19sChIJGTBcB4ome0gR-ezthIqcPo4?authuser=0&hl=en&rclk=1",
    "rating": 5.0,
    "total_reviews": 137,
    "business_status": "OPERATIONAL",
    "opening_hours": "{\"Friday\":[\"Open 24 hours\"],\"Monday\":[\"Open 24 hours\"],\"Saturday\":[\"Open 24 hours\"],\"Sunday\":[\"Open 24 hours\"],\"Thursday\":[\"Open 24 hours\"],\"Tuesday\":[\"Open 24 hours\"],\"Wednesday\":[\"Open 24 hours\"]}",
    "types": "Coach and minibus hire",
    "lat": 53.416259,
    "lng": -3.027245,
    "found_in_location": "Wallasey",
    "found_with_query": "limo wales"
  },
  {
    "name": "American Car Weddings",
    "address": "Edge Hill, Tavern Y Coed, Cardiff, Tonteg, Pontypridd, CF38 1LH, GB",
    "phone": "07759 724226",
    "international_phone": "07759 724226",
    "website": "https://www.americancarweddings.co.uk/",
    "google_maps_url": "https://www.google.com/maps/place/American+Car+Weddings/data=!4m7!3m6!1s0x486e1765d85c253f:0xecdd610c570bc2b5!8m2!3d51.578279!4d-3.3146224!16s%2Fg%2F11f1vpptgk!19sChIJPyVc2GUXbkgRtcILVwxh3ew?authuser=0&hl=en&rclk=1",
    "rating": 5.0,
    "total_reviews": 103,
    "business_status": "OPERATIONAL",
    "opening_hours": "{\"Friday\":[\"8\u202fam\u201310\u202fpm\"],\"Monday\":[\"8\u202fam\u201310\u202fpm\"],\"Saturday\":[\"8\u202fam\u201310\u202fpm\"],\"Sunday\":[\"8\u202fam\u20138\u202fpm\"],\"Thursday\":[\"8\u202fam\u201310\u202fpm\"],\"Tuesday\":[\"8\u202fam\u201310\u202fpm\"],\"Wednesday\":[\"8\u202fam\u201310\u202fpm\"]}",
    "types": "Wedding service",
    "lat": 51.578279,
    "lng": -3.314622,
    "found_in_location": "Pontypridd",
    "found_with_query": "limo wales"
  },
  {
    "name": "Bolers Travel Services Ltd",
    "address": "Barley-Fields Industrial Estate, Nantyglo, Ebbw Vale, NP23 4YF, GB",
    "phone": "07493 811172",
    "international_phone": "07493 811172",
    "website": "",
    "google_maps_url": "https://www.google.com/maps/place/Bolers+Travel+Services+Ltd/data=!4m7!3m6!1s0x486e26ee32f04065:0x7471747069b9859b!8m2!3d51.7934724!4d-3.1715475!16s%2Fg%2F11dz26tbd3!19sChIJZUDwMu4mbkgRm4W5aXB0cXQ?authuser=0&hl=en&rclk=1",
    "rating": 5.0,
    "total_reviews": 59,
    "business_status": "OPERATIONAL",
    "opening_hours": "{\"Friday\":[\"9\u202fam\u20133\u202fpm\"],\"Monday\":[\"9\u202fam\u20133\u202fpm\"],\"Saturday\":[\"9\u202fam\u20132\u202fpm\"],\"Sunday\":[\"Closed\"],\"Thursday\":[\"9\u202fam\u20133\u202fpm\"],\"Tuesday\":[\"9\u202fam\u20133\u202fpm\"],\"Wednesday\":[\"9\u202fam\u20133\u202fpm\"]}",
    "types": "Coach and minibus hire",
    "lat": 51.793472,
    "lng": -3.171547,
    "found_in_location": "Ebbw Vale",
    "found_with_query": "limo wales"
  },
  {
    "name": "CAB X",
    "address": "5 Caxton Pl, Bridge St, Baneswell, Newport, NP20 4BN, GB",
    "phone": "01633 500500",
    "international_phone": "01633 500500",
    "website": "https://cabx.uk/",
    "google_maps_url": "https://www.google.com/maps/place/CAB+X/data=!4m7!3m6!1s0x81c887cb9ccf9b7:0x64a818c5af571681!8m2!3d51.587331!4d-2.9997762!16s%2Fg%2F11mrzg2nfh!19sChIJt_nMuXyIHAgRgRZXr8UYqGQ?authuser=0&hl=en&rclk=1",
    "rating": 5.0,
    "total_reviews": 46,
    "business_status": "OPERATIONAL",
    "opening_hours": "{}",
    "types": "Taxi service",
    "lat": 51.587331,
    "lng": -2.999776,
    "found_in_location": "Newport",
    "found_with_query": "limo wales"
  },
  {
    "name": "J&L Elite Travel Ltd",
    "address": "Bridge Rd, Wrexham, LL13 9SQ, GB",
    "phone": "07999 010609",
    "international_phone": "07999 010609",
    "website": "https://www.jandlelitetravel.co.uk/",
    "google_maps_url": "https://www.google.com/maps/place/J%26L+Elite+Travel+Ltd/data=!4m7!3m6!1s0xadb43f5a3d1db323:0x2d21d3b672fe22f7!8m2!3d53.0323183!4d-2.9363989!16s%2Fg%2F11wjdz4tf_!19sChIJI7MdPVo_tK0R9yL-crbTIS0?authuser=0&hl=en&rclk=1",
    "rating": 5.0,
    "total_reviews": 39,
    "business_status": "OPERATIONAL",
    "opening_hours": "{}",
    "types": "Taxi service",
    "lat": 53.032318,
    "lng": -2.936399,
    "found_in_location": "Wrexham",
    "found_with_query": "limo wales"
  },
  {
    "name": "Cardiff Diamond Transport",
    "address": "31 Appledore Rd, Cardiff, CF14 3HU, GB",
    "phone": "07590 848852",
    "international_phone": "07590 848852",
    "website": "https://cardiffdiamondtransport.com/",
    "google_maps_url": "https://www.google.com/maps/place/Cardiff+Diamond+Transport/data=!4m7!3m6!1s0x486e1bbdacb5f8b5:0xdc2143576a878f0!8m2!3d51.5043569!4d-3.2020918!16s%2Fg%2F11mdhzs7c1!19sChIJtfi1rL0bbkgR8HiodjUUwg0?authuser=0&hl=en&rclk=1",
    "rating": 5.0,
    "total_reviews": 39,
    "business_status": "OPERATIONAL",
    "opening_hours": "{}",
    "types": "Taxi service",
    "lat": 51.504357,
    "lng": -3.202092,
    "found_in_location": "Cardiff",
    "found_with_query": "limo wales"
  },
  {
    "name": "Ebony & Ivory Wedding Cars Ltd",
    "address": "3 Mountjoy Pl, Penarth, CF64 2TB, GB",
    "phone": "",
    "international_phone": "",
    "website": "https://www.ebonyandivoryweddings.co.uk/",
    "google_maps_url": "https://www.google.com/maps/place/Ebony+%26+Ivory+Wedding+Cars+Ltd/data=!4m7!3m6!1s0x486e037da2ba4e75:0xa66a3bde86a0dd07!8m2!3d51.4369895!4d-3.1875632!16s%2Fg%2F1jglth11g!19sChIJdU66on0DbkgRB92ght47aqY?authuser=0&hl=en&rclk=1",
    "rating": 5.0,
    "total_reviews": 38,
    "business_status": "OPERATIONAL",
    "opening_hours": "{\"Friday\":[\"8\u202fam\u201310\u202fpm\"],\"Monday\":[\"8\u202fam\u201310\u202fpm\"],\"Saturday\":[\"8\u202fam\u201310\u202fpm\"],\"Sunday\":[\"8\u202fam\u201310\u202fpm\"],\"Thursday\":[\"8\u202fam\u201310\u202fpm\"],\"Tuesday\":[\"8\u202fam\u201310\u202fpm\"],\"Wednesday\":[\"8\u202fam\u201310\u202fpm\"]}",
    "types": "Wedding service",
    "lat": 51.436989,
    "lng": -3.187563,
    "found_in_location": "Penarth",
    "found_with_query": "limo wales"
  },
  {
    "name": "Morgan\u2019s Minibus and airport shuttle service",
    "address": "Load of Hay Rd, Newbridge, Newport, NP11 3AQ, GB",
    "phone": "07500 375935",
    "international_phone": "07500 375935",
    "website": "http://morgansminibus.com/?utm_source=gmb&utm_medium=referral",
    "google_maps_url": "https://www.google.com/maps/place/Morgan%E2%80%99s+Minibus+and+airport+shuttle+service/data=!4m7!3m6!1s0x486e218e67765157:0x40f631e599b3da2f!8m2!3d51.6843406!4d-3.1488397!16s%2Fg%2F11fmtjcw44!19sChIJV1F2Z44hbkgRL9qzmeUx9kA?authuser=0&hl=en&rclk=1",
    "rating": 5.0,
    "total_reviews": 37,
    "business_status": "OPERATIONAL",
    "opening_hours": "{}",
    "types": "Airport shuttle service",
    "lat": 51.684341,
    "lng": -3.14884,
    "found_in_location": "Newport",
    "found_with_query": "limo wales"
  },
  {
    "name": "Angels Wedding Cars NI",
    "address": "Belgravia Grn, Bangor, BT19 6XF, GB",
    "phone": "07904 391836",
    "international_phone": "07904 391836",
    "website": "http://angelweddingcars.com/",
    "google_maps_url": "https://www.google.com/maps/place/Angels+Wedding+Cars+NI/data=!4m7!3m6!1s0x4861761b428a6d33:0xc53b74dcf18572ca!8m2!3d54.6486536!4d-5.6235525!16s%2Fg%2F11f5h7rpvw!19sChIJM22KQht2YUgRynKF8dx0O8U?authuser=0&hl=en&rclk=1",
    "rating": 5.0,
    "total_reviews": 33,
    "business_status": "OPERATIONAL",
    "opening_hours": "{\"Friday\":[\"10\u202fam\u20135\u202fpm\"],\"Monday\":[\"10\u202fam\u20135\u202fpm\"],\"Saturday\":[\"Closed\"],\"Sunday\":[\"Closed\"],\"Thursday\":[\"10\u202fam\u20135\u202fpm\"],\"Tuesday\":[\"10\u202fam\u20135\u202fpm\"],\"Wednesday\":[\"10\u202fam\u20135\u202fpm\"]}",
    "types": "Wedding service",
    "lat": 54.648654,
    "lng": -5.623552,
    "found_in_location": "Bangor",
    "found_with_query": "limo wales"
  },
  {
    "name": "Mora Chauffeur Prestige",
    "address": "60 Arthur St, Tonypandy, Tonypandy, CF40 1NE, GB",
    "phone": "07376 975469",
    "international_phone": "07376 975469",
    "website": "https://mcpcars.com/",
    "google_maps_url": "https://www.google.com/maps/place/Mora+Chauffeur+Prestige/data=!4m7!3m6!1s0x486e150409042d81:0x2a9023caf58cca6e!8m2!3d51.606685!4d-3.4414274!16s%2Fg%2F11y5m2wn3y!19sChIJgS0ECQQVbkgRbsqM9cojkCo?authuser=0&hl=en&rclk=1",
    "rating": 5.0,
    "total_reviews": 28,
    "business_status": "OPERATIONAL",
    "opening_hours": "{\"Friday\":[\"7\u202fam\u20139\u202fpm\"],\"Monday\":[\"7\u202fam\u20139\u202fpm\"],\"Saturday\":[\"7\u202fam\u20139\u202fpm\"],\"Sunday\":[\"7\u202fam\u20139\u202fpm\"],\"Thursday\":[\"7\u202fam\u20139\u202fpm\"],\"Tuesday\":[\"7\u202fam\u20139\u202fpm\"],\"Wednesday\":[\"7\u202fam\u20139\u202fpm\"]}",
    "types": "Chauffeur service",
    "lat": 51.606685,
    "lng": -3.441427,
    "found_in_location": "Tonypandy",
    "found_with_query": "limo wales"
  },
  {
    "name": "Tabby's Travel",
    "address": "33 Rassau Rd, Rassau, Ebbw Vale, NP23 5SH, GB",
    "phone": "07765 157983",
    "international_phone": "07765 157983",
    "website": "",
    "google_maps_url": "https://www.google.com/maps/place/Tabby%27s+Travel/data=!4m7!3m6!1s0x486e260fc24e65b9:0xd073b102374b25bc!8m2!3d51.7962831!4d-3.2190701!16s%2Fg%2F11j00s7dd3!19sChIJuWVOwg8mbkgRvCVLNwKxc9A?authuser=0&hl=en&rclk=1",
    "rating": 5.0,
    "total_reviews": 26,
    "business_status": "OPERATIONAL",
    "opening_hours": "{\"Friday\":[\"Open 24 hours\"],\"Monday\":[\"Open 24 hours\"],\"Saturday\":[\"Open 24 hours\"],\"Sunday\":[\"Open 24 hours\"],\"Thursday\":[\"Open 24 hours\"],\"Tuesday\":[\"Open 24 hours\"],\"Wednesday\":[\"Open 24 hours\"]}",
    "types": "Transportation service",
    "lat": 51.796283,
    "lng": -3.21907,
    "found_in_location": "Ebbw Vale",
    "found_with_query": "limo wales"
  },
  {
    "name": "MH Travel North Wales",
    "address": "Butchers Market, High St, Wrexham, LL13 8HY, GB",
    "phone": "01978 534280",
    "international_phone": "01978 534280",
    "website": "https://www.mhtravelnorthwales.co.uk/?utm_source=google&utm_medium=wix_google_business_profile&utm_campaign=1450023104214124369",
    "google_maps_url": "https://www.google.com/maps/place/MH+Travel+North+Wales/data=!4m7!3m6!1s0x4643f0cdd06ee915:0xc1e2b2d0e3b46704!8m2!3d53.0453819!4d-2.9922941!16s%2Fg%2F11vc040k96!19sChIJFelu0M3wQ0YRBGe049Cy4sE?authuser=0&hl=en&rclk=1",
    "rating": 5.0,
    "total_reviews": 23,
    "business_status": "OPERATIONAL",
    "opening_hours": "{\"Friday\":[\"Open 24 hours\"],\"Monday\":[\"Open 24 hours\"],\"Saturday\":[\"Open 24 hours\"],\"Sunday\":[\"Open 24 hours\"],\"Thursday\":[\"Open 24 hours\"],\"Tuesday\":[\"Open 24 hours\"],\"Wednesday\":[\"Open 24 hours\"]}",
    "types": "Coach and minibus hire",
    "lat": 53.045382,
    "lng": -2.992294,
    "found_in_location": "Wrexham",
    "found_with_query": "limo wales"
  },
  {
    "name": "Happy Days Cars",
    "address": "26 Second Ave, Caerphilly, CF83 2SN, GB",
    "phone": "07853 145966",
    "international_phone": "07853 145966",
    "website": "https://happydayscars.co.uk/",
    "google_maps_url": "https://www.google.com/maps/place/Happy+Days+Cars/data=!4m7!3m6!1s0x486e1957706a877b:0x8b07900c70748686!8m2!3d51.5781984!4d-3.234968!16s%2Fg%2F11stpnfd8_!19sChIJe4dqcFcZbkgRhoZ0cAyQB4s?authuser=0&hl=en&rclk=1",
    "rating": 5.0,
    "total_reviews": 18,
    "business_status": "OPERATIONAL",
    "opening_hours": "{\"Friday\":[\"9\u202fam\u20135\u202fpm\"],\"Monday\":[\"9\u202fam\u20135\u202fpm\"],\"Saturday\":[\"9\u202fam\u20135\u202fpm\"],\"Sunday\":[\"9\u202fam\u20135\u202fpm\"],\"Thursday\":[\"9\u202fam\u20135\u202fpm\"],\"Tuesday\":[\"9\u202fam\u20135\u202fpm\"],\"Wednesday\":[\"9\u202fam\u20135\u202fpm\"]}",
    "types": "Wedding service",
    "lat": 51.578198,
    "lng": -3.234968,
    "found_in_location": "Caerphilly",
    "found_with_query": "limo wales"
  },
  {
    "name": "Retro Hire Wales",
    "address": "195 St Teilo St, Pontarddulais, Swansea, SA4 8LQ, GB",
    "phone": "07967 490506",
    "international_phone": "07967 490506",
    "website": "http://retrohirewales.co.uk/",
    "google_maps_url": "https://www.google.com/maps/place/Retro+Hire+Wales/data=!4m7!3m6!1s0x486ef1b1737c4dbb:0x39d6d042a234fb6c!8m2!3d51.7119165!4d-4.0351181!16s%2Fg%2F11p4qmf4pg!19sChIJu018c7HxbkgRbPs0okLQ1jk?authuser=0&hl=en&rclk=1",
    "rating": 5.0,
    "total_reviews": 9,
    "business_status": "OPERATIONAL",
    "opening_hours": "{\"Friday\":[\"Open 24 hours\"],\"Monday\":[\"Open 24 hours\"],\"Saturday\":[\"Open 24 hours\"],\"Sunday\":[\"Open 24 hours\"],\"Thursday\":[\"Open 24 hours\"],\"Tuesday\":[\"Open 24 hours\"],\"Wednesday\":[\"Open 24 hours\"]}",
    "types": "Car rental company",
    "lat": 51.711917,
    "lng": -4.035118,
    "found_in_location": "Swansea",
    "found_with_query": "limo wales"
  },
  {
    "name": "Chris\u2019s Luxury Travel",
    "address": "3 Haig Rd, Wrexham, LL13 7BU, GB",
    "phone": "0800 118 2452",
    "international_phone": "0800 118 2452",
    "website": "http://www.chrisluxurytravel.co.uk/",
    "google_maps_url": "https://www.google.com/maps/place/Chris%E2%80%99s+Luxury+Travel/data=!4m7!3m6!1s0x487ac71765e70d3b:0xf83974d9006bae92!8m2!3d53.0401535!4d-2.9880478!16s%2Fg%2F1thmkjht!19sChIJOw3nZRfHekgRkq5rANl0Ofg?authuser=0&hl=en&rclk=1",
    "rating": 5.0,
    "total_reviews": 8,
    "business_status": "OPERATIONAL",
    "opening_hours": "{}",
    "types": "Airport shuttle service",
    "lat": 53.040153,
    "lng": -2.988048,
    "found_in_location": "Wrexham",
    "found_with_query": "limo wales"
  },
  {
    "name": "VW Weddings Wales",
    "address": "Pontygwindy Rd, Caerphilly, CF83 3AB, GB",
    "phone": "",
    "international_phone": "",
    "website": "http://www.vwweddingswales.co.uk/",
    "google_maps_url": "https://www.google.com/maps/place/VW+Weddings+Wales/data=!4m7!3m6!1s0x486e1939dde003ff:0xfc874edc07ea7023!8m2!3d51.580282!4d-3.2181522!16s%2Fg%2F1hdzpnv6k!19sChIJ_wPg3TkZbkgRI3DqB9xOh_w?authuser=0&hl=en&rclk=1",
    "rating": 5.0,
    "total_reviews": 7,
    "business_status": "OPERATIONAL",
    "opening_hours": "{\"Friday\":[\"9\u202fam\u20136\u202fpm\"],\"Monday\":[\"9\u202fam\u20136\u202fpm\"],\"Saturday\":[\"9\u202fam\u20134\u202fpm\"],\"Sunday\":[\"Closed\"],\"Thursday\":[\"9\u202fam\u20136\u202fpm\"],\"Tuesday\":[\"9\u202fam\u20136\u202fpm\"],\"Wednesday\":[\"9\u202fam\u20136\u202fpm\"]}",
    "types": "Wedding service",
    "lat": 51.580282,
    "lng": -3.218152,
    "found_in_location": "Caerphilly",
    "found_with_query": "limo wales"
  },
  {
    "name": "Thomas Coaches Ltd",
    "address": "Plot 10, Ogmore Vale, Bridgend, CF32 7AX, GB",
    "phone": "01656 769889",
    "international_phone": "01656 769889",
    "website": "",
    "google_maps_url": "https://www.google.com/maps/place/Thomas+Coaches+Ltd/data=!4m7!3m6!1s0x486e6b34228e62af:0x12f5b57e476382ee!8m2!3d51.6077178!4d-3.5415745!16s%2Fg%2F11rd1jy5zp!19sChIJr2KOIjRrbkgR7oJjR3619RI?authuser=0&hl=en&rclk=1",
    "rating": 5.0,
    "total_reviews": 5,
    "business_status": "OPERATIONAL",
    "opening_hours": "{\"Friday\":[\"9\u202fam\u20135\u202fpm\"],\"Monday\":[\"9\u202fam\u20135\u202fpm\"],\"Saturday\":[\"9\u202fam\u20135\u202fpm\"],\"Sunday\":[\"9\u202fam\u20135\u202fpm\"],\"Thursday\":[\"9\u202fam\u20135\u202fpm\"],\"Tuesday\":[\"9\u202fam\u20135\u202fpm\"],\"Wednesday\":[\"9\u202fam\u20135\u202fpm\"]}",
    "types": "Coach and minibus hire",
    "lat": 51.607718,
    "lng": -3.541574,
    "found_in_location": "Bridgend",
    "found_with_query": "limo wales"
  },
  {
    "name": "My Day Wedding Cars",
    "address": "9 Shirley Dr, Heolgerrig, Merthyr Tydfil, CF48 1SE, GB",
    "phone": "07780 814791",
    "international_phone": "07780 814791",
    "website": "http://mydayweddingcars.co.uk/",
    "google_maps_url": "https://www.google.com/maps/place/My+Day+Wedding+Cars/data=!4m7!3m6!1s0x486e3bc0cb395555:0xd09727618b147c71!8m2!3d51.7449577!4d-3.4033859!16s%2Fg%2F11w2_ch3yk!19sChIJVVU5y8A7bkgRcXwUi2Enl9A?authuser=0&hl=en&rclk=1",
    "rating": 5.0,
    "total_reviews": 5,
    "business_status": "OPERATIONAL",
    "opening_hours": "{}",
    "types": "Wedding service",
    "lat": 51.744958,
    "lng": -3.403386,
    "found_in_location": "Merthyr Tydfil",
    "found_with_query": "limo wales"
  },
  {
    "name": "Meirion Williams & Son",
    "address": "Cae Rodyn, Pantllyn Terrace, Pantllyn, Llandybie, Ammanford, SA18 3JU, GB",
    "phone": "01269 832389",
    "international_phone": "01269 832389",
    "website": "",
    "google_maps_url": "https://www.google.com/maps/place/Meirion+Williams+%26+Son/data=!4m7!3m6!1s0x486ef973b5dc646b:0xd3110626b01f0d10!8m2!3d51.8333045!4d-4.0298453!16s%2Fg%2F1tfch5xq!19sChIJa2TctXP5bkgREA0fsCYGEdM?authuser=0&hl=en&rclk=1",
    "rating": 5.0,
    "total_reviews": 4,
    "business_status": "OPERATIONAL",
    "opening_hours": "{}",
    "types": "Trucking company",
    "lat": 51.833304,
    "lng": -4.029845,
    "found_in_location": "Ammanford",
    "found_with_query": "limo wales"
  },
  {
    "name": "South Wales Wedding Cars",
    "address": "54 Snowdon Ct, Cwmbran, NP44 2JB, GB",
    "phone": "07715 583822",
    "international_phone": "07715 583822",
    "website": "https://southwalesweddingcars.co.uk/",
    "google_maps_url": "https://www.google.com/maps/place/South+Wales+Wedding+Cars/data=!4m7!3m6!1s0x4871dde1e830b8e3:0x84db7547f21206e9!8m2!3d51.6619259!4d-3.0128061!16s%2Fg%2F1hc1g8gbm!19sChIJ47gw6OHdcUgR6QYS8kd124Q?authuser=0&hl=en&rclk=1",
    "rating": 5.0,
    "total_reviews": 4,
    "business_status": "OPERATIONAL",
    "opening_hours": "{\"Friday\":[\"9\u202fam\u20135\u202fpm\"],\"Monday\":[\"9\u202fam\u20135\u202fpm\"],\"Saturday\":[\"9\u202fam\u20135\u202fpm\"],\"Sunday\":[\"Closed\"],\"Thursday\":[\"9\u202fam\u20135\u202fpm\"],\"Tuesday\":[\"9\u202fam\u20135\u202fpm\"],\"Wednesday\":[\"9\u202fam\u20135\u202fpm\"]}",
    "types": "Wedding service",
    "lat": 51.661926,
    "lng": -3.012806,
    "found_in_location": "Cwmbran",
    "found_with_query": "limo wales"
  },
  {
    "name": "Arrive In Style",
    "address": "46 Maesteg Rd, Tondu, Bridgend, CF32 9BT, GB",
    "phone": "01656 723869",
    "international_phone": "01656 723869",
    "website": "",
    "google_maps_url": "https://www.google.com/maps/place/Arrive+In+Style/data=!4m7!3m6!1s0x486e6bf8cca13115:0x753ee43796da2fe!8m2!3d51.5450026!4d-3.5978662!16s%2Fg%2F1trxjq7g!19sChIJFTGhzPhrbkgR_qJteUPuUwc?authuser=0&hl=en&rclk=1",
    "rating": 5.0,
    "total_reviews": 4,
    "business_status": "OPERATIONAL",
    "opening_hours": "{}",
    "types": "Limousine service",
    "lat": 51.545003,
    "lng": -3.597866,
    "found_in_location": "Bridgend",
    "found_with_query": "limo wales"
  },
  {
    "name": "ABC Executive Travel (Chauffeur Service)",
    "address": "Duxford Cl, Llandaff, Cardiff, CF5 2PR, GB",
    "phone": "07564 564664",
    "international_phone": "07564 564664",
    "website": "https://www.abcexecutivetravel.co.uk/",
    "google_maps_url": "https://www.google.com/maps/place/ABC+Executive+Travel+%28Chauffeur+Service%29/data=!4m7!3m6!1s0x486e1b1ceae6c9ad:0x5daeb7845aac021d!8m2!3d51.50052!4d-3.2417239!16s%2Fg%2F11dylsk1p0!19sChIJrcnm6hwbbkgRHQKsWoS3rl0?authuser=0&hl=en&rclk=1",
    "rating": 5.0,
    "total_reviews": 4,
    "business_status": "OPERATIONAL",
    "opening_hours": "{}",
    "types": "Taxi service",
    "lat": 51.50052,
    "lng": -3.241724,
    "found_in_location": "Cardiff",
    "found_with_query": "limo wales"
  },
  {
    "name": "Bay Executive Wedding and Airport Travel",
    "address": "11 St Helen's Rd, Swansea, SA1 4AW, GB",
    "phone": "07956 431961",
    "international_phone": "07956 431961",
    "website": "",
    "google_maps_url": "https://www.google.com/maps/place/Bay+Executive+Wedding+and+Airport+Travel/data=!4m7!3m6!1s0x486ef4b75bbe8d35:0x6e3d4d54f445db9f!8m2!3d51.6187044!4d-3.9510855!16s%2Fg%2F11c1pdt1s8!19sChIJNY2-W7f0bkgRn9tF9FRNPW4?authuser=0&hl=en&rclk=1",
    "rating": 5.0,
    "total_reviews": 4,
    "business_status": "OPERATIONAL",
    "opening_hours": "{\"Friday\":[\"8\u202fam\u20135:30\u202fpm\"],\"Monday\":[\"8\u202fam\u20135:30\u202fpm\"],\"Saturday\":[\"8\u202fam\u20135:30\u202fpm\"],\"Sunday\":[\"8:30\u202fam\u20135:30\u202fpm\"],\"Thursday\":[\"8\u202fam\u20135:30\u202fpm\"],\"Tuesday\":[\"8\u202fam\u20135:30\u202fpm\"],\"Wednesday\":[\"8\u202fam\u20135:30\u202fpm\"]}",
    "types": "Wedding service",
    "lat": 51.618704,
    "lng": -3.951086,
    "found_in_location": "Swansea",
    "found_with_query": "limo wales"
  },
  {
    "name": "Executive Cars Wales Ltd",
    "address": "Unit 4B, Westwinds Business Park, Llangan, Bridgend, CF35 5DR, GB",
    "phone": "01656 857793",
    "international_phone": "01656 857793",
    "website": "https://www.executivecarswales.co.uk/",
    "google_maps_url": "https://www.google.com/maps/place/Executive+Cars+Wales+Ltd/data=!4m7!3m6!1s0x486e13440e3717a9:0x70169e9332536316!8m2!3d51.4882598!4d-3.486009!16s%2Fg%2F11vwpfgj93!19sChIJqRc3DkQTbkgRFmNTMpOeFnA?authuser=0&hl=en&rclk=1",
    "rating": 5.0,
    "total_reviews": 3,
    "business_status": "OPERATIONAL",
    "opening_hours": "{\"Friday\":[\"9\u202fam\u20135\u202fpm\"],\"Monday\":[\"9\u202fam\u20135\u202fpm\"],\"Saturday\":[\"Closed\"],\"Sunday\":[\"Closed\"],\"Thursday\":[\"9\u202fam\u20135\u202fpm\"],\"Tuesday\":[\"9\u202fam\u20135\u202fpm\"],\"Wednesday\":[\"9\u202fam\u20135\u202fpm\"]}",
    "types": "Chauffeur service",
    "lat": 51.48826,
    "lng": -3.486009,
    "found_in_location": "Bridgend",
    "found_with_query": "limo wales"
  },
  {
    "name": "M J N Travel",
    "address": "8 Greenwood Pl, Portmead, Swansea, SA5 5HQ, GB",
    "phone": "01792 586712",
    "international_phone": "01792 586712",
    "website": "http://www.mjntravel.co.uk/",
    "google_maps_url": "https://www.google.com/maps/place/M+J+N+Travel/data=!4m7!3m6!1s0x486ef4fbfc7948f1:0xcc4814476f421ab0!8m2!3d51.6540747!4d-3.9838087!16s%2Fg%2F11b6jkhqxm!19sChIJ8Uh5_Pv0bkgRsBpCb0cUSMw?authuser=0&hl=en&rclk=1",
    "rating": 5.0,
    "total_reviews": 3,
    "business_status": "OPERATIONAL",
    "opening_hours": "{\"Friday\":[\"9\u202fam\u20139\u202fpm\"],\"Monday\":[\"9\u202fam\u20139\u202fpm\"],\"Saturday\":[\"9\u202fam\u20139\u202fpm\"],\"Sunday\":[\"9\u202fam\u20139\u202fpm\"],\"Thursday\":[\"9\u202fam\u20139\u202fpm\"],\"Tuesday\":[\"9\u202fam\u20139\u202fpm\"],\"Wednesday\":[\"9\u202fam\u20139\u202fpm\"]}",
    "types": "Coach and minibus hire",
    "lat": 51.654075,
    "lng": -3.983809,
    "found_in_location": "Swansea",
    "found_with_query": "limo wales"
  },
  {
    "name": "Denway Travel",
    "address": "10 Y Llest, Pen-y-fai, Bridgend, CF31 4NA, GB",
    "phone": "01656 725266",
    "international_phone": "01656 725266",
    "website": "",
    "google_maps_url": "https://www.google.com/maps/place/Denway+Travel/data=!4m7!3m6!1s0x486e6c1eb3155b8d:0x7360adbac79a849!8m2!3d51.527508!4d-3.59533!16s%2Fg%2F1q66wnmpv!19sChIJjVsVsx5sbkgRSah5rNsKNgc?authuser=0&hl=en&rclk=1",
    "rating": 5.0,
    "total_reviews": 2,
    "business_status": "OPERATIONAL",
    "opening_hours": "{\"Friday\":[\"12:01\u202fam\u201311:59\u202fpm\"],\"Monday\":[\"12:01\u202fam\u201311:59\u202fpm\"],\"Saturday\":[\"12:01\u202fam\u201311:59\u202fpm\"],\"Sunday\":[\"12:01\u202fam\u201311:59\u202fpm\"],\"Thursday\":[\"12:01\u202fam\u201311:59\u202fpm\"],\"Tuesday\":[\"12:01\u202fam\u201311:59\u202fpm\"],\"Wednesday\":[\"12:01\u202fam\u201311:59\u202fpm\"]}",
    "types": "Coach and minibus hire",
    "lat": 51.527508,
    "lng": -3.59533,
    "found_in_location": "Bridgend",
    "found_with_query": "limo wales"
  },
  {
    "name": "M L Executive Chauffeur Services",
    "address": "83 Ynysddu, Pontyclun, CF72 9UB, GB",
    "phone": "07572 015249",
    "international_phone": "07572 015249",
    "website": "http://www.mlexecutivechauffeurservices.com/",
    "google_maps_url": "https://www.google.com/maps/place/M+L+Executive+Chauffeur+Services/data=!4m7!3m6!1s0x486e116729551f09:0x630e44b1c293b85e!8m2!3d51.527334!4d-3.394736!16s%2Fg%2F11fx9cyz4k!19sChIJCR9VKWcRbkgRXriTwrFEDmM?authuser=0&hl=en&rclk=1",
    "rating": 5.0,
    "total_reviews": 2,
    "business_status": "OPERATIONAL",
    "opening_hours": "{\"Friday\":[\"9\u202fam\u20139\u202fpm\"],\"Monday\":[\"9\u202fam\u20139\u202fpm\"],\"Saturday\":[\"9\u202fam\u20139\u202fpm\"],\"Sunday\":[\"9\u202fam\u20139\u202fpm\"],\"Thursday\":[\"9\u202fam\u20139\u202fpm\"],\"Tuesday\":[\"9\u202fam\u20139\u202fpm\"],\"Wednesday\":[\"9\u202fam\u20139\u202fpm\"]}",
    "types": "Chauffeur service",
    "lat": 51.527334,
    "lng": -3.394736,
    "found_in_location": "Pontyclun",
    "found_with_query": "limo wales"
  },
  {
    "name": "DrivenByQ Chauffeur for Business Travel",
    "address": "St. Andrews House, Yale Business Village, Ellice Way, Wrexham, LL13 7YP, GB",
    "phone": "01978 846678",
    "international_phone": "01978 846678",
    "website": "https://drivenbyq.com/",
    "google_maps_url": "https://www.google.com/maps/place/DrivenByQ+Chauffeur+for+Business+Travel/data=!4m7!3m6!1s0x487ac7aaf5ee0349:0x59eb5b91754398ff!8m2!3d53.0496672!4d-3.0079757!16s%2Fg%2F1tf30yg2!19sChIJSQPu9arHekgR_5hDdZFb61k?authuser=0&hl=en&rclk=1",
    "rating": 5.0,
    "total_reviews": 1,
    "business_status": "OPERATIONAL",
    "opening_hours": "{\"Friday\":[\"8\u202fam\u20135\u202fpm\"],\"Monday\":[\"8\u202fam\u20135:30\u202fpm\"],\"Saturday\":[\"9\u202fam\u201312\u202fpm\"],\"Sunday\":[\"Closed\"],\"Thursday\":[\"8\u202fam\u20135:30\u202fpm\"],\"Tuesday\":[\"8\u202fam\u20135:30\u202fpm\"],\"Wednesday\":[\"8\u202fam\u20135:30\u202fpm\"]}",
    "types": "Transportation service",
    "lat": 53.049667,
    "lng": -3.007976,
    "found_in_location": "Wrexham",
    "found_with_query": "limo wales"
  },
  {
    "name": "Castell Coaches",
    "address": "9, Trecenydd Business Park, Caerphilly, CF83 2RZ, GB",
    "phone": "029 2086 1863",
    "international_phone": "029 2086 1863",
    "website": "",
    "google_maps_url": "https://www.google.com/maps/place/Castell+Coaches/data=!4m7!3m6!1s0x486e19151e7d0d85:0x1f315b2394d594ab!8m2!3d51.5773963!4d-3.2333756!16s%2Fg%2F11c3tj9yn4!19sChIJhQ19HhUZbkgRq5TVlCNbMR8?authuser=0&hl=en&rclk=1",
    "rating": 5.0,
    "total_reviews": 1,
    "business_status": "OPERATIONAL",
    "opening_hours": "{}",
    "types": "Limousine service",
    "lat": 51.577396,
    "lng": -3.233376,
    "found_in_location": "Caerphilly",
    "found_with_query": "limo wales"
  },
  {
    "name": "1st Class Weddings",
    "address": "45 Waun Bant Road, Kenfig Hill, Bridgend, CF33 6DE, GB",
    "phone": "07884 314818",
    "international_phone": "07884 314818",
    "website": "",
    "google_maps_url": "https://www.google.com/maps/place/1st+Class+Weddings/data=!4m7!3m6!1s0x486e6f480a6c0efd:0xf438dbbaf42d0ecb!8m2!3d51.5307209!4d-3.6775358!16s%2Fg%2F1jkvz5b3f!19sChIJ_Q5sCkhvbkgRyw4t9LrbOPQ?authuser=0&hl=en&rclk=1",
    "rating": 5.0,
    "total_reviews": 1,
    "business_status": "OPERATIONAL",
    "opening_hours": "{\"Friday\":[\"9\u202fam\u201310\u202fpm\"],\"Monday\":[\"9\u202fam\u201310\u202fpm\"],\"Saturday\":[\"Closed\"],\"Sunday\":[\"Closed\"],\"Thursday\":[\"9\u202fam\u201310\u202fpm\"],\"Tuesday\":[\"9\u202fam\u201310\u202fpm\"],\"Wednesday\":[\"9\u202fam\u201310\u202fpm\"]}",
    "types": "Wedding service",
    "lat": 51.530721,
    "lng": -3.677536,
    "found_in_location": "Bridgend",
    "found_with_query": "limo wales"
  },
  {
    "name": "Prestige Chauffeurs Cardiff Ltd (Chauffeur Service )",
    "address": "Sophia House, 28 Cathedral Rd, Pontcanna, Cardiff, CF11 9LJ, GB",
    "phone": "0330 043 6403",
    "international_phone": "0330 043 6403",
    "website": "http://www.pchauffeurscardiff.co.uk/",
    "google_maps_url": "https://www.google.com/maps/place/Prestige+Chauffeurs+Cardiff+Ltd+%28Chauffeur+Service+%29/data=!4m7!3m6!1s0x486e1cf6aab523a1:0x88ad1faeaea260e8!8m2!3d51.4843128!4d-3.1914753!16s%2Fg%2F11f3w9r7l3!19sChIJoSO1qvYcbkgR6GCirq4frYg?authuser=0&hl=en&rclk=1",
    "rating": 4.9,
    "total_reviews": 72,
    "business_status": "OPERATIONAL",
    "opening_hours": "{\"Friday\":[\"Open 24 hours\"],\"Monday\":[\"Open 24 hours\"],\"Saturday\":[\"Open 24 hours\"],\"Sunday\":[\"Open 24 hours\"],\"Thursday\":[\"Open 24 hours\"],\"Tuesday\":[\"Open 24 hours\"],\"Wednesday\":[\"Open 24 hours\"]}",
    "types": "Chauffeur service",
    "lat": 51.484313,
    "lng": -3.191475,
    "found_in_location": "Cardiff",
    "found_with_query": "limo wales"
  },
  {
    "name": "iDoo Wedding Cars",
    "address": "14 Douglas Cl, Cardiff, CF5 2QT, GB",
    "phone": "07823 556846",
    "international_phone": "07823 556846",
    "website": "http://idooweddingcarscardiff.co.uk/",
    "google_maps_url": "https://www.google.com/maps/place/iDoo+Wedding+Cars/data=!4m7!3m6!1s0x486e1b1b1df30c3b:0x3d4dce7b373339dc!8m2!3d51.500148!4d-3.2371122!16s%2Fg%2F11bx0dwc7z!19sChIJOwzzHRsbbkgR3DkzN3vOTT0?authuser=0&hl=en&rclk=1",
    "rating": 4.9,
    "total_reviews": 65,
    "business_status": "OPERATIONAL",
    "opening_hours": "{\"Friday\":[\"9:30\u202fam\u20138\u202fpm\"],\"Monday\":[\"9:30\u202fam\u20138\u202fpm\"],\"Saturday\":[\"9:30\u202fam\u20136\u202fpm\"],\"Sunday\":[\"10:30\u202fam\u20134\u202fpm\"],\"Thursday\":[\"9:30\u202fam\u20138\u202fpm\"],\"Tuesday\":[\"9:30\u202fam\u20138\u202fpm\"],\"Wednesday\":[\"9:30\u202fam\u20138\u202fpm\"]}",
    "types": "Wedding service",
    "lat": 51.500148,
    "lng": -3.237112,
    "found_in_location": "Cardiff",
    "found_with_query": "limo wales"
  },
  {
    "name": "Swansea Limos",
    "address": "Nantyffin South, Swansea Enterprise Park, Llansamlet, Swansea, SA7 9RG, GB",
    "phone": "01792 475000",
    "international_phone": "01792 475000",
    "website": "https://www.swansealimos.co.uk/",
    "google_maps_url": "https://www.google.com/maps/place/Swansea+Limos/data=!4m7!3m6!1s0x486ef560795f5ec7:0xfe35d559ba2ac85c!8m2!3d51.654005!4d-3.908029!16s%2Fg%2F1tlmmrsg!19sChIJx15feWD1bkgRXMgqulnVNf4?authuser=0&hl=en&rclk=1",
    "rating": 4.9,
    "total_reviews": 41,
    "business_status": "OPERATIONAL",
    "opening_hours": "{\"Friday\":[\"9\u202fam\u20136\u202fpm\"],\"Monday\":[\"9\u202fam\u20136\u202fpm\"],\"Saturday\":[\"9\u202fam\u20136\u202fpm\"],\"Sunday\":[\"9\u202fam\u20136\u202fpm\"],\"Thursday\":[\"9\u202fam\u20136\u202fpm\"],\"Tuesday\":[\"9\u202fam\u20136\u202fpm\"],\"Wednesday\":[\"9\u202fam\u20136\u202fpm\"]}",
    "types": "Transportation service",
    "lat": 51.654005,
    "lng": -3.908029,
    "found_in_location": "Swansea",
    "found_with_query": "limo wales"
  },
  {
    "name": "Gwyn Jones & Son Ltd",
    "address": "Whitecroft Garage, Bryncethin, CF32 9YR, GB",
    "phone": "01656 720300",
    "international_phone": "01656 720300",
    "website": "http://www.gwynjonescoaches.co.uk/",
    "google_maps_url": "https://www.google.com/maps/place/Gwyn+Jones+%26+Son+Ltd/data=!4m7!3m6!1s0x486e6b88298d0a0b:0x5493e1754cf3b23e!8m2!3d51.545106!4d-3.568675!16s%2Fg%2F1td7smg9!19sChIJCwqNKYhrbkgRPrLzTHXhk1Q?authuser=0&hl=en&rclk=1",
    "rating": 4.9,
    "total_reviews": 20,
    "business_status": "OPERATIONAL",
    "opening_hours": "{}",
    "types": "Bus company",
    "lat": 51.545106,
    "lng": -3.568675,
    "found_in_location": "Bryncethin",
    "found_with_query": "limo wales"
  },
  {
    "name": "Big Day Wedding Cars",
    "address": "Unit 3 Blackwood Rd, Pontllanfraith, Blackwood, NP12 2BW, GB",
    "phone": "07452 865414",
    "international_phone": "07452 865414",
    "website": "http://www.bigdayweddingcars.co.uk/",
    "google_maps_url": "https://www.google.com/maps/place/Big+Day+Wedding+Cars/data=!4m7!3m6!1s0x486e21f0ea4e4cd3:0x4fd64f2cf2324942!8m2!3d51.6569092!4d-3.191461!16s%2Fg%2F11fy2vqc0h!19sChIJ00xO6vAhbkgRQkky8ixP1k8?authuser=0&hl=en&rclk=1",
    "rating": 4.9,
    "total_reviews": 15,
    "business_status": "OPERATIONAL",
    "opening_hours": "{\"Friday\":[\"9\u202fam\u20135\u202fpm\"],\"Monday\":[\"8\u202fam\u20138\u202fpm\"],\"Saturday\":[\"9\u202fam\u20135\u202fpm\"],\"Sunday\":[\"9\u202fam\u20135\u202fpm\"],\"Thursday\":[\"9\u202fam\u20135\u202fpm\"],\"Tuesday\":[\"9\u202fam\u20135\u202fpm\"],\"Wednesday\":[\"9\u202fam\u20135\u202fpm\"]}",
    "types": "Wedding service",
    "lat": 51.656909,
    "lng": -3.191461,
    "found_in_location": "Blackwood",
    "found_with_query": "limo wales"
  },
  {
    "name": "Truck & Bus Services",
    "address": "Unit 4, F. Lloyd (Penley) Ltd, Bridge Rd S, Wrexham, LL13 9SQ, GB",
    "phone": "01978 855506",
    "international_phone": "01978 855506",
    "website": "",
    "google_maps_url": "https://www.google.com/maps/place/Truck+%26+Bus+Services/data=!4m7!3m6!1s0x487ac41e539a9be5:0x6c6c5d1af7106c83!8m2!3d53.030738!4d-2.9369441!16s%2Fg%2F1tdvzf4t!19sChIJ5ZuaUx7EekgRg2wQ9xpdbGw?authuser=0&hl=en&rclk=1",
    "rating": 4.9,
    "total_reviews": 13,
    "business_status": "OPERATIONAL",
    "opening_hours": "{\"Friday\":[\"8\u202fam\u20135\u202fpm\"],\"Monday\":[\"8\u202fam\u20135\u202fpm\"],\"Saturday\":[\"7\u202fam\u20131\u202fpm\"],\"Sunday\":[\"Closed\"],\"Thursday\":[\"8\u202fam\u20135\u202fpm\"],\"Tuesday\":[\"8\u202fam\u20135\u202fpm\"],\"Wednesday\":[\"8\u202fam\u20135\u202fpm\"]}",
    "types": "Truck repair shop",
    "lat": 53.030738,
    "lng": -2.936944,
    "found_in_location": "Wrexham",
    "found_with_query": "limo wales"
  },
  {
    "name": "Glyn's Wedding Cars",
    "address": "rose cottage, Mynydd Cerrig, Llanelli, SA15 5BD, GB",
    "phone": "07970 038531",
    "international_phone": "07970 038531",
    "website": "",
    "google_maps_url": "https://www.google.com/maps/place/Glyn%27s+Wedding+Cars/data=!4m7!3m6!1s0x486ee53795138101:0xc2cbc2f1fa0401b9!8m2!3d51.802709!4d-4.158193!16s%2Fg%2F1hc636c_w!19sChIJAYETlTflbkgRuQEE-vHCy8I?authuser=0&hl=en&rclk=1",
    "rating": 4.9,
    "total_reviews": 7,
    "business_status": "OPERATIONAL",
    "opening_hours": "{}",
    "types": "Limousine service",
    "lat": 51.802709,
    "lng": -4.158193,
    "found_in_location": "Llanelli",
    "found_with_query": "limo wales"
  },
  {
    "name": "Lakeside Venue",
    "address": "Glyn Ogwr, Blackmill, Bridgend, CF35 6EN, GB",
    "phone": "01443 674840",
    "international_phone": "01443 674840",
    "website": "http://lakesidevenue.co.uk/",
    "google_maps_url": "https://www.google.com/maps/place/Lakeside+Venue/data=!4m7!3m6!1s0x486e6cf95f49c877:0x5e32c0900d4f0174!8m2!3d51.582344!4d-3.48022!16s%2Fg%2F12hrygk2w!19sChIJd8hJX_lsbkgRdAFPDZDAMl4?authuser=0&hl=en&rclk=1",
    "rating": 4.8,
    "total_reviews": 204,
    "business_status": "OPERATIONAL",
    "opening_hours": "{\"Friday\":[\"10\u202fam\u20136\u202fpm\"],\"Monday\":[\"10\u202fam\u20136\u202fpm\"],\"Saturday\":[\"10\u202fam\u20136\u202fpm\"],\"Sunday\":[\"10\u202fam\u20136\u202fpm\"],\"Thursday\":[\"10\u202fam\u20136\u202fpm\"],\"Tuesday\":[\"10\u202fam\u20136\u202fpm\"],\"Wednesday\":[\"10\u202fam\u20136\u202fpm\"]}",
    "types": "Wedding venue",
    "lat": 51.582344,
    "lng": -3.48022,
    "found_in_location": "Bridgend",
    "found_with_query": "limo wales"
  },
  {
    "name": "Wrexham Chauffeurs Ltd",
    "address": "38 Ithens Way, Wrexham, LL13 7EQ, GB",
    "phone": "01978 253815",
    "international_phone": "01978 253815",
    "website": "https://wrexhamchauffeurs.co.uk/",
    "google_maps_url": "https://www.google.com/maps/place/Wrexham+Chauffeurs+Ltd/data=!4m7!3m6!1s0x487ac73a69c2ab35:0x588b5a4d2e90683a!8m2!3d53.0327438!4d-2.9886134!16s%2Fg%2F1tdz4cbj!19sChIJNavCaTrHekgROmiQLk1ai1g?authuser=0&hl=en&rclk=1",
    "rating": 4.8,
    "total_reviews": 65,
    "business_status": "OPERATIONAL",
    "opening_hours": "{\"Friday\":[\"Open 24 hours\"],\"Monday\":[\"Open 24 hours\"],\"Saturday\":[\"Open 24 hours\"],\"Sunday\":[\"Open 24 hours\"],\"Thursday\":[\"Open 24 hours\"],\"Tuesday\":[\"Open 24 hours\"],\"Wednesday\":[\"Open 24 hours\"]}",
    "types": "Transportation service",
    "lat": 53.032744,
    "lng": -2.988613,
    "found_in_location": "Wrexham",
    "found_with_query": "limo wales"
  },
  {
    "name": "LCC",
    "address": "92 Red House Rd, Cardiff, CF5 4FH, GB",
    "phone": "07778 158351",
    "international_phone": "07778 158351",
    "website": "",
    "google_maps_url": "https://www.google.com/maps/place/LCC/data=!4m7!3m6!1s0x486e1b3dde2b61bd:0x3d6f68ee4caf8f6c!8m2!3d51.4836069!4d-3.248752!16s%2Fg%2F11rxptbhgn!19sChIJvWEr3j0bbkgRbI-vTO5obz0?authuser=0&hl=en&rclk=1",
    "rating": 4.8,
    "total_reviews": 24,
    "business_status": "OPERATIONAL",
    "opening_hours": "{\"Friday\":[\"Open 24 hours\"],\"Monday\":[\"Open 24 hours\"],\"Saturday\":[\"Open 24 hours\"],\"Sunday\":[\"Open 24 hours\"],\"Thursday\":[\"Open 24 hours\"],\"Tuesday\":[\"Open 24 hours\"],\"Wednesday\":[\"Open 24 hours\"]}",
    "types": "Chauffeur service",
    "lat": 51.483607,
    "lng": -3.248752,
    "found_in_location": "Cardiff",
    "found_with_query": "limo wales"
  },
  {
    "name": "Twisted Hen & Stag Parties",
    "address": "Cardiff, CF10, GB",
    "phone": "07450 891479",
    "international_phone": "07450 891479",
    "website": "https://www.epicmoments.uk/",
    "google_maps_url": "https://www.google.com/maps/place/Twisted+Hen+%26+Stag+Parties/data=!4m7!3m6!1s0x486e1cccf289d54f:0x3c918cdf176fe2b!8m2!3d51.4697688!4d-3.1649216!16s%2Fg%2F1thx80sx!19sChIJT9WJ8swcbkgRK_528c0YyQM?authuser=0&hl=en&rclk=1",
    "rating": 4.8,
    "total_reviews": 20,
    "business_status": "OPERATIONAL",
    "opening_hours": "{\"Friday\":[\"Open 24 hours\"],\"Monday\":[\"Open 24 hours\"],\"Saturday\":[\"Open 24 hours\"],\"Sunday\":[\"Open 24 hours\"],\"Thursday\":[\"Open 24 hours\"],\"Tuesday\":[\"Open 24 hours\"],\"Wednesday\":[\"Open 24 hours\"]}",
    "types": "Entertainment agency",
    "lat": 51.469769,
    "lng": -3.164922,
    "found_in_location": "Cardiff",
    "found_with_query": "limo wales"
  },
  {
    "name": "Dubs Travels",
    "address": "Cragside Cl, Saint Mellons, Cardiff, CF3 0HU, GB",
    "phone": "07793 129328",
    "international_phone": "07793 129328",
    "website": "https://www.dubstravels.co.uk/",
    "google_maps_url": "https://www.google.com/maps/place/Dubs+Travels/data=!4m7!3m6!1s0x486e1dda74b24537:0xe079eaf0f4c5c40f!8m2!3d51.5225096!4d-3.0993731!16s%2Fg%2F11sq3mdc8m!19sChIJN0WydNodbkgRD8TF9PDqeeA?authuser=0&hl=en&rclk=1",
    "rating": 4.8,
    "total_reviews": 18,
    "business_status": "OPERATIONAL",
    "opening_hours": "{\"Friday\":[\"Open 24 hours\"],\"Monday\":[\"Open 24 hours\"],\"Saturday\":[\"Open 24 hours\"],\"Sunday\":[\"Open 24 hours\"],\"Thursday\":[\"Open 24 hours\"],\"Tuesday\":[\"Open 24 hours\"],\"Wednesday\":[\"Open 24 hours\"]}",
    "types": "Coach and minibus hire",
    "lat": 51.52251,
    "lng": -3.099373,
    "found_in_location": "Cardiff",
    "found_with_query": "limo wales"
  },
  {
    "name": "Straffords Coaches Ltd",
    "address": "Units 7 & 8, Five Crosses Industrial Estate, Minera, Coedpoeth, Wrexham, LL11 3RD, GB",
    "phone": "01978 756106",
    "international_phone": "01978 756106",
    "website": "https://www.straffordscoaches.co.uk/",
    "google_maps_url": "https://www.google.com/maps/place/Straffords+Coaches+Ltd/data=!4m7!3m6!1s0x487ac890066c8fe9:0x9534c1f045bb0f55!8m2!3d53.0610778!4d-3.0780016!16s%2Fg%2F1tfnsjsy!19sChIJ6Y9sBpDIekgRVQ-7RfDBNJU?authuser=0&hl=en&rclk=1",
    "rating": 4.8,
    "total_reviews": 16,
    "business_status": "OPERATIONAL",
    "opening_hours": "{\"Friday\":[\"9\u202fam\u20135\u202fpm\"],\"Monday\":[\"9\u202fam\u20135\u202fpm\"],\"Saturday\":[\"Closed\"],\"Sunday\":[\"Closed\"],\"Thursday\":[\"9\u202fam\u20135\u202fpm\"],\"Tuesday\":[\"9\u202fam\u20135\u202fpm\"],\"Wednesday\":[\"9\u202fam\u20135\u202fpm\"]}",
    "types": "Coach and minibus hire",
    "lat": 53.061078,
    "lng": -3.078002,
    "found_in_location": "Wrexham",
    "found_with_query": "limo wales"
  },
  {
    "name": "Prices Wedding Cars",
    "address": "Unit B1, Fram Enterprise Centre Edwards Business Park, Ynysmaerdy, Pontyclun, CF72 8YU, GB",
    "phone": "01443 201940",
    "international_phone": "01443 201940",
    "website": "http://www.pricesweddingcars.co.uk/",
    "google_maps_url": "https://www.google.com/maps/place/Prices+Wedding+Cars/data=!4m7!3m6!1s0x486e1732f9192f3b:0x9de42743f6b8bcf2!8m2!3d51.5522113!4d-3.3908489!16s%2Fg%2F1hc1_w639!19sChIJOy8Z-TIXbkgR8ry49kMn5J0?authuser=0&hl=en&rclk=1",
    "rating": 4.8,
    "total_reviews": 16,
    "business_status": "OPERATIONAL",
    "opening_hours": "{\"Friday\":[\"10:30\u202fam\u20134:30\u202fpm\"],\"Monday\":[\"Closed\"],\"Saturday\":[\"10:30\u202fam\u20134\u202fpm\"],\"Sunday\":[\"Closed\"],\"Thursday\":[\"10:30\u202fam\u20133\u202fpm\"],\"Tuesday\":[\"10:30\u202fam\u20137\u202fpm\"],\"Wednesday\":[\"10:30\u202fam\u20133\u202fpm\"]}",
    "types": "Limousine service",
    "lat": 51.552211,
    "lng": -3.390849,
    "found_in_location": "Pontyclun",
    "found_with_query": "limo wales"
  },
  {
    "name": "Valentines Travel",
    "address": "Unit 12, Ruabon, Wrexham, LL14 6HA, GB",
    "phone": "01978 844450",
    "international_phone": "01978 844450",
    "website": "",
    "google_maps_url": "https://www.google.com/maps/place/Valentines+Travel/data=!4m7!3m6!1s0x487ac7fc6a47282f:0x767133be804588a8!8m2!3d53.0010458!4d-3.0389995!16s%2Fg%2F1thwzznb!19sChIJLyhHavzHekgRqIhFgL4zcXY?authuser=0&hl=en&rclk=1",
    "rating": 4.8,
    "total_reviews": 15,
    "business_status": "OPERATIONAL",
    "opening_hours": "{\"Friday\":[\"Open 24 hours\"],\"Monday\":[\"Open 24 hours\"],\"Saturday\":[\"Open 24 hours\"],\"Sunday\":[\"Open 24 hours\"],\"Thursday\":[\"Open 24 hours\"],\"Tuesday\":[\"Open 24 hours\"],\"Wednesday\":[\"Open 24 hours\"]}",
    "types": "Company",
    "lat": 53.001046,
    "lng": -3.039,
    "found_in_location": "Wrexham",
    "found_with_query": "limo wales"
  },
  {
    "name": "Game Station Bus Gaming Van",
    "address": "Meadow Sweet Dr, Saint Mellons, Cardiff, CF3 0RD, GB",
    "phone": "07562 530002",
    "international_phone": "07562 530002",
    "website": "https://www.gamestationbus.co.uk/",
    "google_maps_url": "https://www.google.com/maps/place/Game+Station+Bus+Gaming+Van/data=!4m7!3m6!1s0x281292d25a74bf7d:0xdb5fb406d1daa59a!8m2!3d51.5200314!4d-3.0896461!16s%2Fg%2F11y48t_vls!19sChIJfb90WtKSEigRmqXa0Qa0X9s?authuser=0&hl=en&rclk=1",
    "rating": 4.7,
    "total_reviews": 29,
    "business_status": "OPERATIONAL",
    "opening_hours": "{\"Friday\":[\"7\u202fam\u20139\u202fpm\"],\"Monday\":[\"7\u202fam\u20139\u202fpm\"],\"Saturday\":[\"7\u202fam\u20139\u202fpm\"],\"Sunday\":[\"7\u202fam\u20139\u202fpm\"],\"Thursday\":[\"7\u202fam\u20139\u202fpm\"],\"Tuesday\":[\"7\u202fam\u20139\u202fpm\"],\"Wednesday\":[\"7\u202fam\u20139\u202fpm\"]}",
    "types": "Children's party service",
    "lat": 51.520031,
    "lng": -3.089646,
    "found_in_location": "Cardiff",
    "found_with_query": "limo wales"
  },
  {
    "name": "Voel Coaches Ltd",
    "address": "Long Acre, Road, Dyserth, Rhyl, LL18 6BP, GB",
    "phone": "01745 570154",
    "international_phone": "01745 570154",
    "website": "http://www.voelholidays.com/",
    "google_maps_url": "https://www.google.com/maps/place/Voel+Coaches+Ltd/data=!4m7!3m6!1s0x4865298493196035:0xcab544972246eda1!8m2!3d53.3056462!4d-3.4208437!16s%2Fg%2F1trxjps0!19sChIJNWAZk4QpZUgRoe1GIpdEtco?authuser=0&hl=en&rclk=1",
    "rating": 4.6,
    "total_reviews": 356,
    "business_status": "OPERATIONAL",
    "opening_hours": "{\"Friday\":[\"9\u202fam\u20135\u202fpm\"],\"Monday\":[\"9\u202fam\u20135\u202fpm\"],\"Saturday\":[\"8\u202fam\u201312\u202fpm\"],\"Sunday\":[\"Closed\"],\"Thursday\":[\"9\u202fam\u20135\u202fpm\"],\"Tuesday\":[\"9\u202fam\u20135\u202fpm\"],\"Wednesday\":[\"9\u202fam\u20135\u202fpm\"]}",
    "types": "Tours",
    "lat": 53.305646,
    "lng": -3.420844,
    "found_in_location": "Rhyl",
    "found_with_query": "limo wales"
  },
  {
    "name": "The Limo People Ltd",
    "address": "50a, Symondscliffe Way, Severn Bridge Industrial Estate, Caldicot, NP26 5PW, GB",
    "phone": "0800 180 4128",
    "international_phone": "0800 180 4128",
    "website": "https://www.thelimopeople.co.uk/",
    "google_maps_url": "https://www.google.com/maps/place/The+Limo+People+Ltd/data=!4m7!3m6!1s0x4871eb6b430db243:0x65ff44b33e49fb19!8m2!3d51.586795!4d-2.7388636!16s%2Fg%2F1tncsbs5!19sChIJQ7INQ2vrcUgRGftJPrNE_2U?authuser=0&hl=en&rclk=1",
    "rating": 4.6,
    "total_reviews": 49,
    "business_status": "OPERATIONAL",
    "opening_hours": "{\"Friday\":[\"9\u202fam\u20136\u202fpm\"],\"Monday\":[\"9\u202fam\u20136\u202fpm\"],\"Saturday\":[\"Closed\"],\"Sunday\":[\"Closed\"],\"Thursday\":[\"9\u202fam\u20136\u202fpm\"],\"Tuesday\":[\"9\u202fam\u20136\u202fpm\"],\"Wednesday\":[\"9\u202fam\u20136\u202fpm\"]}",
    "types": "Limousine service",
    "lat": 51.586795,
    "lng": -2.738864,
    "found_in_location": "Caldicot",
    "found_with_query": "limo wales"
  },
  {
    "name": "Bryngarw House",
    "address": "Brynmenyn, Bridgend, CF32 8UU, GB",
    "phone": "01656 729009",
    "international_phone": "01656 729009",
    "website": "http://www.bryngarwhouse.com/",
    "google_maps_url": "https://www.google.com/maps/place/Bryngarw+House/data=!4m10!3m9!1s0x486e037034273669:0x91e27330389e2b18!5m2!4m1!1i2!8m2!3d51.558261!4d-3.581462!16s%2Fg%2F1tdp4gw2!19sChIJaTYnNHADbkgRGCueODBz4pE?authuser=0&hl=en&rclk=1",
    "rating": 4.5,
    "total_reviews": 353,
    "business_status": "OPERATIONAL",
    "opening_hours": "{}",
    "types": "Wedding venue",
    "lat": 51.558261,
    "lng": -3.581462,
    "found_in_location": "Bridgend",
    "found_with_query": "limo wales"
  },
  {
    "name": "Cathays Community Centre",
    "address": "36-38 Cathays Terrace, Cardiff, CF24 4HX, GB",
    "phone": "029 2037 3144",
    "international_phone": "029 2037 3144",
    "website": "https://www.cathays.org.uk/",
    "google_maps_url": "https://www.google.com/maps/place/Cathays+Community+Centre/data=!4m7!3m6!1s0x486e1cbd12d8849b:0x83f26044f4dfd1d5!8m2!3d51.491697!4d-3.180694!16s%2Fg%2F1thtp09d!19sChIJm4TYEr0cbkgR1dHf9ERg8oM?authuser=0&hl=en&rclk=1",
    "rating": 4.5,
    "total_reviews": 260,
    "business_status": "OPERATIONAL",
    "opening_hours": "{\"Friday\":[\"9\u202fam\u201310\u202fpm\"],\"Monday\":[\"9\u202fam\u201310\u202fpm\"],\"Saturday\":[\"9\u202fam\u201310\u202fpm\"],\"Sunday\":[\"9\u202fam\u201310\u202fpm\"],\"Thursday\":[\"9\u202fam\u201310\u202fpm\"],\"Tuesday\":[\"9\u202fam\u201310\u202fpm\"],\"Wednesday\":[\"9\u202fam\u201310\u202fpm\"]}",
    "types": "Community centre",
    "lat": 51.491697,
    "lng": -3.180694,
    "found_in_location": "Cardiff",
    "found_with_query": "limo wales"
  },
  {
    "name": "Pat's Coaches",
    "address": "Derwen House, Southsea Rd, Southsea, Wrexham, LL11 6PP, GB",
    "phone": "01978 720171",
    "international_phone": "01978 720171",
    "website": "http://www.patscoaches.co.uk/",
    "google_maps_url": "https://www.google.com/maps/place/Pat%27s+Coaches/data=!4m7!3m6!1s0x487ac64d754ff1e9:0xeafea9ab7ca20653!8m2!3d53.056135!4d-3.0360594!16s%2Fg%2F1tr7hx_q!19sChIJ6fFPdU3GekgRUwaifKup_uo?authuser=0&hl=en&rclk=1",
    "rating": 4.5,
    "total_reviews": 251,
    "business_status": "OPERATIONAL",
    "opening_hours": "{}",
    "types": "Bus company",
    "lat": 53.056135,
    "lng": -3.036059,
    "found_in_location": "Wrexham",
    "found_with_query": "limo wales"
  },
  {
    "name": "Gibbons Coaches",
    "address": "Ty Cerbyd, 8 George St, Bedlinog, Treharris, CF46 6RT, GB",
    "phone": "01443 710604",
    "international_phone": "01443 710604",
    "website": "https://www.gibbonscoaches.com/",
    "google_maps_url": "https://www.google.com/maps/place/Gibbons+Coaches/data=!4m7!3m6!1s0x486e23493121a863:0x8a139887a8467f90!8m2!3d51.7037338!4d-3.3113341!16s%2Fg%2F1tn056xz!19sChIJY6ghMUkjbkgRkH9GqIeYE4o?authuser=0&hl=en&rclk=1",
    "rating": 4.4,
    "total_reviews": 101,
    "business_status": "OPERATIONAL",
    "opening_hours": "{}",
    "types": "Bus company",
    "lat": 51.703734,
    "lng": -3.311334,
    "found_in_location": "Treharris",
    "found_with_query": "limo wales"
  },
  {
    "name": "Day's Rental | Bridgend",
    "address": "David St, Bridgend, CF31 3SA, GB",
    "phone": "01656 808099",
    "international_phone": "01656 808099",
    "website": "http://www.daysrental.co.uk/",
    "google_maps_url": "https://www.google.com/maps/place/Day%27s+Rental+%7C+Bridgend/data=!4m7!3m6!1s0x486e6d0290665cab:0x68fdd99ddc8f2716!8m2!3d51.502802!4d-3.539431!16s%2Fg%2F1tff712n!19sChIJq1xmkAJtbkgRFieP3J3Z_Wg?authuser=0&hl=en&rclk=1",
    "rating": 4.4,
    "total_reviews": 34,
    "business_status": "OPERATIONAL",
    "opening_hours": "{\"Friday\":[\"8\u202fam\u20135:30\u202fpm\"],\"Monday\":[\"8\u202fam\u20135:30\u202fpm\"],\"Saturday\":[\"8\u202fam\u201312:30\u202fpm\"],\"Sunday\":[\"Closed\"],\"Thursday\":[\"8\u202fam\u20135:30\u202fpm\"],\"Tuesday\":[\"8\u202fam\u20135:30\u202fpm\"],\"Wednesday\":[\"8\u202fam\u20135:30\u202fpm\"]}",
    "types": "Car rental company",
    "lat": 51.502802,
    "lng": -3.539431,
    "found_in_location": "Bridgend",
    "found_with_query": "limo wales"
  },
  {
    "name": "Cheringham Wedding Cars Cardiff",
    "address": "Cheringham Cottage, Whitson, Newport, NP18 2PG, GB",
    "phone": "01633 290002",
    "international_phone": "01633 290002",
    "website": "https://cheringhamcars.co.uk/?utm_source=Gmap&utm_medium=Gmap&utm_campaign=Google+Map&utm_id=Gmap",
    "google_maps_url": "https://www.google.com/maps/place/Cheringham+Wedding+Cars+Cardiff/data=!4m7!3m6!1s0x4871efe4bf268f6d:0x7eec6ed403ee15ce!8m2!3d51.550133!4d-2.9000835!16s%2Fg%2F11j90ymymk!19sChIJbY8mv-TvcUgRzhXuA9Ru7H4?authuser=0&hl=en&rclk=1",
    "rating": 4.4,
    "total_reviews": 20,
    "business_status": "OPERATIONAL",
    "opening_hours": "{}",
    "types": "Car rental company",
    "lat": 51.550133,
    "lng": -2.900084,
    "found_in_location": "Newport",
    "found_with_query": "limo wales"
  },
  {
    "name": "Gower Mini Travel",
    "address": "White Lodge, Swansea Rd, Gorseinon, Swansea, SA4 4LQ, GB",
    "phone": "01792 895777",
    "international_phone": "01792 895777",
    "website": "http://www.gowerminitravel.co.uk/",
    "google_maps_url": "https://www.google.com/maps/place/Gower+Mini+Travel/data=!4m7!3m6!1s0x486ef47e1fc2d5af:0x6e8d36c65406e41a!8m2!3d51.6567197!4d-4.0193197!16s%2Fg%2F1tdd98kl!19sChIJr9XCH370bkgRGuQGVMY2jW4?authuser=0&hl=en&rclk=1",
    "rating": 4.4,
    "total_reviews": 10,
    "business_status": "OPERATIONAL",
    "opening_hours": "{\"Friday\":[\"8:30\u202fam\u20135\u202fpm\"],\"Monday\":[\"8:30\u202fam\u20135\u202fpm\"],\"Saturday\":[\"Closed\"],\"Sunday\":[\"Closed\"],\"Thursday\":[\"8:30\u202fam\u20135\u202fpm\"],\"Tuesday\":[\"8:30\u202fam\u20135\u202fpm\"],\"Wednesday\":[\"8:30\u202fam\u20135\u202fpm\"]}",
    "types": "Coach and minibus hire",
    "lat": 51.65672,
    "lng": -4.01932,
    "found_in_location": "Swansea",
    "found_with_query": "limo wales"
  },
  {
    "name": "Coastal Mini Coaches",
    "address": "42 Maes-Y-Capel, Pembrey, Llanelli, Burry Port, SA16 0EG, GB",
    "phone": "07789 988721",
    "international_phone": "07789 988721",
    "website": "http://www.coastalminicoaches.co.uk/",
    "google_maps_url": "https://www.google.com/maps/place/Coastal+Mini+Coaches/data=!4m7!3m6!1s0x486eebd9084eb5b7:0xa4238a66a3680499!8m2!3d51.6869354!4d-4.2695096!16s%2Fg%2F1tlzzm16!19sChIJt7VOCNnrbkgRmQRoo2aKI6Q?authuser=0&hl=en&rclk=1",
    "rating": 4.4,
    "total_reviews": 7,
    "business_status": "OPERATIONAL",
    "opening_hours": "{\"Friday\":[\"9\u202fam\u20136\u202fpm\"],\"Monday\":[\"9\u202fam\u20136\u202fpm\"],\"Saturday\":[\"Closed\"],\"Sunday\":[\"Closed\"],\"Thursday\":[\"9\u202fam\u20136\u202fpm\"],\"Tuesday\":[\"9\u202fam\u20136\u202fpm\"],\"Wednesday\":[\"9\u202fam\u20136\u202fpm\"]}",
    "types": "Coach and minibus hire",
    "lat": 51.686935,
    "lng": -4.26951,
    "found_in_location": "Burry Port",
    "found_with_query": "limo wales"
  },
  {
    "name": "The Cobbles Collective",
    "address": "Tymaen Farm Buildings, Ogmore Rd, Ogmore-by-Sea, Bridgend, CF32 0QP, GB",
    "phone": "01656 646361",
    "international_phone": "01656 646361",
    "website": "http://www.cobblescollective.co.uk/",
    "google_maps_url": "https://www.google.com/maps/place/The+Cobbles+Collective/data=!4m7!3m6!1s0x486e6e12bb05691f:0x83d878358d064ff6!8m2!3d51.4821373!4d-3.5945242!16s%2Fg%2F11cjkvsk60!19sChIJH2kFuxJubkgR9k8GjTV42IM?authuser=0&hl=en&rclk=1",
    "rating": 4.3,
    "total_reviews": 1104,
    "business_status": "OPERATIONAL",
    "opening_hours": "{\"Friday\":[\"9:30\u202fam\u20134\u202fpm\"],\"Monday\":[\"9:30\u202fam\u20134\u202fpm\"],\"Saturday\":[\"9:30\u202fam\u20134\u202fpm\"],\"Sunday\":[\"9:30\u202fam\u20134\u202fpm\"],\"Thursday\":[\"9:30\u202fam\u20134\u202fpm\"],\"Tuesday\":[\"9:30\u202fam\u20134\u202fpm\"],\"Wednesday\":[\"9:30\u202fam\u20134\u202fpm\"]}",
    "types": "Wedding venue",
    "lat": 51.482137,
    "lng": -3.594524,
    "found_in_location": "Bridgend",
    "found_with_query": "limo wales"
  },
  {
    "name": "Creigiau Travel Ltd",
    "address": "Station Rd, Creigiau, Cardiff, CF15 9NT, GB",
    "phone": "029 2089 0220",
    "international_phone": "029 2089 0220",
    "website": "http://www.creigiautravel.co.uk/",
    "google_maps_url": "https://www.google.com/maps/place/Creigiau+Travel+Ltd/data=!4m7!3m6!1s0x486e1a7f635119c5:0x61d28d8058fd25b5!8m2!3d51.5248575!4d-3.3224187!16s%2Fg%2F1vq748py!19sChIJxRlRY38abkgRtSX9WICN0mE?authuser=0&hl=en&rclk=1",
    "rating": 4.3,
    "total_reviews": 70,
    "business_status": "OPERATIONAL",
    "opening_hours": "{\"Friday\":[\"8\u202fam\u20135\u202fpm\"],\"Monday\":[\"8\u202fam\u20135\u202fpm\"],\"Saturday\":[\"Closed\"],\"Sunday\":[\"Closed\"],\"Thursday\":[\"8\u202fam\u20135\u202fpm\"],\"Tuesday\":[\"8\u202fam\u20135\u202fpm\"],\"Wednesday\":[\"8\u202fam\u20135\u202fpm\"]}",
    "types": "Coach and minibus hire",
    "lat": 51.524857,
    "lng": -3.322419,
    "found_in_location": "Cardiff",
    "found_with_query": "limo wales"
  },
  {
    "name": "Charter Vehicle Hire",
    "address": "Free School Court, Rear of Brackla Street Shopping Centre, Bridgend, CF31 1DD, GB",
    "phone": "01656 652719",
    "international_phone": "01656 652719",
    "website": "http://www.chartervehiclehire.co.uk/index.php",
    "google_maps_url": "https://www.google.com/maps/place/Charter+Vehicle+Hire/data=!4m7!3m6!1s0x486e6c351940746b:0x77638dd8e7da3967!8m2!3d51.5037388!4d-3.5744217!16s%2Fg%2F1tmy4h44!19sChIJa3RAGTVsbkgRZzna59iNY3c?authuser=0&hl=en&rclk=1",
    "rating": 4.3,
    "total_reviews": 43,
    "business_status": "OPERATIONAL",
    "opening_hours": "{\"Friday\":[\"8\u202fam\u20135:30\u202fpm\"],\"Monday\":[\"8\u202fam\u20135:30\u202fpm\"],\"Saturday\":[\"8\u202fam\u201312\u202fpm\"],\"Sunday\":[\"Closed\"],\"Thursday\":[\"8\u202fam\u20135:30\u202fpm\"],\"Tuesday\":[\"8\u202fam\u20135:30\u202fpm\"],\"Wednesday\":[\"8\u202fam\u20135:30\u202fpm\"]}",
    "types": "Car rental company",
    "lat": 51.503739,
    "lng": -3.574422,
    "found_in_location": "Bridgend",
    "found_with_query": "limo wales"
  },
  {
    "name": "Cresta Coaches",
    "address": "Unit 6, Litchard Industrial Estate, Bridgend, CF31 2AL, GB",
    "phone": "01656 660366",
    "international_phone": "01656 660366",
    "website": "http://www.crestacoaches.co.uk/",
    "google_maps_url": "https://www.google.com/maps/place/Cresta+Coaches/data=!4m7!3m6!1s0x486e6c43a160730f:0x3b6dd783be1f2a9e!8m2!3d51.5204341!4d-3.5669018!16s%2Fg%2F1tm292zc!19sChIJD3NgoUNsbkgRniofvoPXbTs?authuser=0&hl=en&rclk=1",
    "rating": 4.3,
    "total_reviews": 35,
    "business_status": "OPERATIONAL",
    "opening_hours": "{\"Friday\":[\"6\u202fam\u20139\u202fpm\"],\"Monday\":[\"6\u202fam\u20139\u202fpm\"],\"Saturday\":[\"9\u202fam\u20135\u202fpm\"],\"Sunday\":[\"9\u202fam\u20133\u202fpm\"],\"Thursday\":[\"6\u202fam\u20139\u202fpm\"],\"Tuesday\":[\"6\u202fam\u20139\u202fpm\"],\"Wednesday\":[\"6\u202fam\u20139\u202fpm\"]}",
    "types": "Coach and minibus hire",
    "lat": 51.520434,
    "lng": -3.566902,
    "found_in_location": "Bridgend",
    "found_with_query": "limo wales"
  },
  {
    "name": "Day's Rental | Newport",
    "address": "Frederick St, Newport, Newport, NP20 2DR, GB",
    "phone": "01633 445022",
    "international_phone": "01633 445022",
    "website": "http://www.daysrental.co.uk/newport",
    "google_maps_url": "https://www.google.com/maps/place/Day%27s+Rental+%7C+Newport/data=!4m7!3m6!1s0x4871e6beb1aebb63:0x69272e4e27adad54!8m2!3d51.578508!4d-2.983794!16s%2Fg%2F1twyy_g2!19sChIJY7uusb7mcUgRVK2tJ04uJ2k?authuser=0&hl=en&rclk=1",
    "rating": 4.3,
    "total_reviews": 35,
    "business_status": "OPERATIONAL",
    "opening_hours": "{\"Friday\":[\"8\u202fam\u20135:30\u202fpm\"],\"Monday\":[\"8\u202fam\u20135:30\u202fpm\"],\"Saturday\":[\"8\u202fam\u201312:30\u202fpm\"],\"Sunday\":[\"Closed\"],\"Thursday\":[\"8\u202fam\u20135:30\u202fpm\"],\"Tuesday\":[\"8\u202fam\u20135:30\u202fpm\"],\"Wednesday\":[\"8\u202fam\u20135:30\u202fpm\"]}",
    "types": "Car rental company",
    "lat": 51.578508,
    "lng": -2.983794,
    "found_in_location": "Newport",
    "found_with_query": "limo wales"
  },
  {
    "name": "1st Choice Ltd",
    "address": "Sandy Rd, Llanelli, SA15 4DP, GB",
    "phone": "01554 759888",
    "international_phone": "01554 759888",
    "website": "http://www.1stchoiceltd.co.uk/",
    "google_maps_url": "https://www.google.com/maps/place/1st+Choice+Ltd/data=!4m7!3m6!1s0x486eec2d24e21cb7:0xda4a6b62b24a7d20!8m2!3d51.6843412!4d-4.1808745!16s%2Fg%2F1tmxd_85!19sChIJtxziJC3sbkgRIH1KsmJrSto?authuser=0&hl=en&rclk=1",
    "rating": 4.3,
    "total_reviews": 21,
    "business_status": "OPERATIONAL",
    "opening_hours": "{}",
    "types": "Bus company",
    "lat": 51.684341,
    "lng": -4.180874,
    "found_in_location": "Llanelli",
    "found_with_query": "limo wales"
  },
  {
    "name": "VMS Vehicle Hire Bridgend",
    "address": "Coychurch, Bridgend, Bridgend, CF35 5NS, GB",
    "phone": "01656 530064",
    "international_phone": "01656 530064",
    "website": "https://www.vmsvehiclehire.co.uk/",
    "google_maps_url": "https://www.google.com/maps/place/VMS+Vehicle+Hire+Bridgend/data=!4m7!3m6!1s0x486e6d8c43aee9a7:0xffaab0dac6d2d92d!8m2!3d51.504632!4d-3.5403437!16s%2Fg%2F11ll7cxtxj!19sChIJp-muQ4xtbkgRLdnSxtqwqv8?authuser=0&hl=en&rclk=1",
    "rating": 4.3,
    "total_reviews": 13,
    "business_status": "OPERATIONAL",
    "opening_hours": "{\"Friday\":[\"8\u202fam\u20136\u202fpm\"],\"Monday\":[\"8\u202fam\u20136\u202fpm\"],\"Saturday\":[\"9\u202fam\u20131\u202fpm\"],\"Sunday\":[\"Closed\"],\"Thursday\":[\"8\u202fam\u20136\u202fpm\"],\"Tuesday\":[\"8\u202fam\u20136\u202fpm\"],\"Wednesday\":[\"8\u202fam\u20136\u202fpm\"]}",
    "types": "Car rental company",
    "lat": 51.504632,
    "lng": -3.540344,
    "found_in_location": "Bridgend",
    "found_with_query": "limo wales"
  },
  {
    "name": "D J Thomas Coaches Ltd",
    "address": "15/16 Old Market St, Neath, SA11 3NA, GB",
    "phone": "01639 635502",
    "international_phone": "01639 635502",
    "website": "http://www.djthomascoaches.com/",
    "google_maps_url": "https://www.google.com/maps/place/D+J+Thomas+Coaches+Ltd/data=!4m7!3m6!1s0x486e5dd1724b5c03:0x6c62b2d528039564!8m2!3d51.6640419!4d-3.8033012!16s%2Fg%2F1tj730b9!19sChIJA1xLctFdbkgRZJUDKNWyYmw?authuser=0&hl=en&rclk=1",
    "rating": 4.2,
    "total_reviews": 53,
    "business_status": "OPERATIONAL",
    "opening_hours": "{\"Friday\":[\"9\u202fam\u20135:30\u202fpm\"],\"Monday\":[\"9\u202fam\u20135:30\u202fpm\"],\"Saturday\":[\"9\u202fam\u20132\u202fpm\"],\"Sunday\":[\"Closed\"],\"Thursday\":[\"9\u202fam\u20135:30\u202fpm\"],\"Tuesday\":[\"9\u202fam\u20135:30\u202fpm\"],\"Wednesday\":[\"9\u202fam\u20135:30\u202fpm\"]}",
    "types": "Coach and minibus hire",
    "lat": 51.664042,
    "lng": -3.803301,
    "found_in_location": "Neath",
    "found_with_query": "limo wales"
  },
  {
    "name": "Unicorn Travel",
    "address": "Unit 1, West Bank Rd, Llay, Wrexham, LL12 0PZ, GB",
    "phone": "01978 856048",
    "international_phone": "01978 856048",
    "website": "https://www.unicorntravelwrexham.co.uk/",
    "google_maps_url": "https://www.google.com/maps/place/Unicorn+Travel/data=!4m7!3m6!1s0x487ac7510133980f:0x4efb40cc9004b248!8m2!3d53.097891!4d-3.004701!16s%2Fg%2F1tfpjbw5!19sChIJD5gzAVHHekgRSLIEkMxA-04?authuser=0&hl=en&rclk=1",
    "rating": 4.2,
    "total_reviews": 9,
    "business_status": "OPERATIONAL",
    "opening_hours": "{\"Friday\":[\"8\u202fam\u20135:30\u202fpm\"],\"Monday\":[\"8\u202fam\u20135:30\u202fpm\"],\"Saturday\":[\"8\u202fam\u201312\u202fpm\"],\"Sunday\":[\"Closed\"],\"Thursday\":[\"8\u202fam\u20135:30\u202fpm\"],\"Tuesday\":[\"8\u202fam\u20135:30\u202fpm\"],\"Wednesday\":[\"8\u202fam\u20135:30\u202fpm\"]}",
    "types": "Coach and minibus hire",
    "lat": 53.097891,
    "lng": -3.004701,
    "found_in_location": "Wrexham",
    "found_with_query": "limo wales"
  },
  {
    "name": "Veezu",
    "address": "Unit 5, Martin Rd, Tremorfa Industrial Estate, Cardiff, CF24 5SD, GB",
    "phone": "029 2033 3333",
    "international_phone": "029 2033 3333",
    "website": "https://www.veezu.co.uk/cardiff?utm_source=GBP+CF24+5SD&utm_medium=GBP&utm_campaign=GBP",
    "google_maps_url": "https://www.google.com/maps/place/Veezu/data=!4m7!3m6!1s0x486e1d31c7a1fb37:0x840527354b026c71!8m2!3d51.4742546!4d-3.1385462!16s%2Fg%2F1tm68c02!19sChIJN_uhxzEdbkgRcWwCSzUnBYQ?authuser=0&hl=en&rclk=1",
    "rating": 4.1,
    "total_reviews": 4164,
    "business_status": "OPERATIONAL",
    "opening_hours": "{}",
    "types": "Taxi service",
    "lat": 51.474255,
    "lng": -3.138546,
    "found_in_location": "Cardiff",
    "found_with_query": "limo wales"
  },
  {
    "name": "Price Coaches",
    "address": "The Haven, Bersham Rd, New Broughton, Wrexham, LL11 6TF, GB",
    "phone": "01978 756834",
    "international_phone": "01978 756834",
    "website": "http://www.pricecoaches.co.uk/",
    "google_maps_url": "https://www.google.com/maps/place/Price+Coaches/data=!4m7!3m6!1s0x487ac64c1991b7c3:0xbe48f776e524f578!8m2!3d53.0544034!4d-3.0311858!16s%2Fg%2F1tqpyskg!19sChIJw7eRGUzGekgRePUk5Xb3SL4?authuser=0&hl=en&rclk=1",
    "rating": 4.1,
    "total_reviews": 9,
    "business_status": "OPERATIONAL",
    "opening_hours": "{\"Friday\":[\"8:30\u202fam\u20135:30\u202fpm\"],\"Monday\":[\"8:30\u202fam\u20136\u202fpm\"],\"Saturday\":[\"Closed\"],\"Sunday\":[\"Closed\"],\"Thursday\":[\"8:30\u202fam\u20136\u202fpm\"],\"Tuesday\":[\"8:30\u202fam\u20136\u202fpm\"],\"Wednesday\":[\"8:30\u202fam\u20136\u202fpm\"]}",
    "types": "Coach and minibus hire",
    "lat": 53.054403,
    "lng": -3.031186,
    "found_in_location": "Wrexham",
    "found_with_query": "limo wales"
  },
  {
    "name": "Cardiff Cruises",
    "address": "Mermaid Quay, Cardiff, CF10 5BZ, GB",
    "phone": "029 2166 1166",
    "international_phone": "029 2166 1166",
    "website": "http://www.cardiffcruises.co.uk/",
    "google_maps_url": "https://www.google.com/maps/place/Cardiff+Cruises/data=!4m7!3m6!1s0x486e0337f6e3b89b:0xadc0743882adab9d!8m2!3d51.4630434!4d-3.1642372!16s%2Fg%2F1hc74z2sy!19sChIJm7jj9jcDbkgRnautgjh0wK0?authuser=0&hl=en&rclk=1",
    "rating": 4.0,
    "total_reviews": 168,
    "business_status": "OPERATIONAL",
    "opening_hours": "{\"Friday\":[\"10:30\u202fam\u20135:30\u202fpm\",\"7:30\u201310:30\u202fpm\"],\"Monday\":[\"10:30\u202fam\u20135:30\u202fpm\"],\"Saturday\":[\"10:30\u202fam\u20135:30\u202fpm\",\"7:30\u201310:30\u202fpm\"],\"Sunday\":[\"10:30\u202fam\u20136:30\u202fpm\"],\"Thursday\":[\"10:30\u202fam\u20135:30\u202fpm\"],\"Tuesday\":[\"10:30\u202fam\u20135:30\u202fpm\"],\"Wednesday\":[\"10:30\u202fam\u20135:30\u202fpm\"]}",
    "types": "Boat tour agency",
    "lat": 51.463043,
    "lng": -3.164237,
    "found_in_location": "Cardiff",
    "found_with_query": "limo wales"
  },
  {
    "name": "Veezu Newport",
    "address": "Station St, Newport, NP20 4AX, GB",
    "phone": "01633 216216",
    "international_phone": "01633 216216",
    "website": "https://www.veezu.co.uk/newport?utm_source=GBP+NP20+4AX&utm_medium=GBP&utm_campaign=GBP",
    "google_maps_url": "https://www.google.com/maps/place/Veezu+Newport/data=!4m7!3m6!1s0x4871e6ce57e00529:0x8ff67147ea81dae!8m2!3d51.5895754!4d-2.998688!16s%2Fg%2F1thn4zkd!19sChIJKQXgV87mcUgRrh2ofhRn_wg?authuser=0&hl=en&rclk=1",
    "rating": 3.8,
    "total_reviews": 2281,
    "business_status": "OPERATIONAL",
    "opening_hours": "{}",
    "types": "Taxi service",
    "lat": 51.589575,
    "lng": -2.998688,
    "found_in_location": "Newport",
    "found_with_query": "limo wales"
  },
  {
    "name": "Elite Travel",
    "address": "56 Pandy Rd, Bedwas, Caerphilly, CF83 8EJ, GB",
    "phone": "029 2088 5180",
    "international_phone": "029 2088 5180",
    "website": "http://www.elitetravelwales.co.uk/",
    "google_maps_url": "https://www.google.com/maps/place/Elite+Travel/data=!4m7!3m6!1s0x486e1ed38c605a39:0x90bf5f3f26eca2a1!8m2!3d51.5922729!4d-3.2032168!16s%2Fg%2F1tfj_8t_!19sChIJOVpgjNMebkgRoaLsJj9fv5A?authuser=0&hl=en&rclk=1",
    "rating": 3.7,
    "total_reviews": 6,
    "business_status": "OPERATIONAL",
    "opening_hours": "{}",
    "types": "Travel Agent",
    "lat": 51.592273,
    "lng": -3.203217,
    "found_in_location": "Caerphilly",
    "found_with_query": "limo wales"
  },
  {
    "name": "Cymru Coaches",
    "address": "Cymru House, Old Training Centre, Westfield Industrial Park, Waunarlwydd, Swansea, SA5 4SF, GB",
    "phone": "01792 583610",
    "international_phone": "01792 583610",
    "website": "http://cymrucoaches.co.uk/",
    "google_maps_url": "https://www.google.com/maps/place/Cymru+Coaches/data=!4m7!3m6!1s0x486ef4ec459421b9:0xc33d4d23dec7fbd3!8m2!3d51.6435828!4d-4.0179625!16s%2Fg%2F1hc5c_xf_!19sChIJuSGURez0bkgR0_vH3iNNPcM?authuser=0&hl=en&rclk=1",
    "rating": 3.4,
    "total_reviews": 42,
    "business_status": "OPERATIONAL",
    "opening_hours": "{\"Friday\":[\"8\u202fam\u20134\u202fpm\"],\"Monday\":[\"8\u202fam\u20134:30\u202fpm\"],\"Saturday\":[\"Closed\"],\"Sunday\":[\"Closed\"],\"Thursday\":[\"8\u202fam\u20134:30\u202fpm\"],\"Tuesday\":[\"8\u202fam\u20134:30\u202fpm\"],\"Wednesday\":[\"8\u202fam\u20134:30\u202fpm\"]}",
    "types": "Coach and minibus hire",
    "lat": 51.643583,
    "lng": -4.017962,
    "found_in_location": "Swansea",
    "found_with_query": "limo wales"
  },
  {
    "name": "Peyton Travel",
    "address": "Brackla Ind. Estate, Main Ave, Bridgend, CF31 2AG, GB",
    "phone": "01656 661221",
    "international_phone": "01656 661221",
    "website": "http://www.peytontravel.co.uk/",
    "google_maps_url": "https://www.google.com/maps/place/Peyton+Travel/data=!4m7!3m6!1s0x486e6db500000001:0x69cd2f90ac05a880!8m2!3d51.5174266!4d-3.5611989!16s%2Fg%2F11g9f4_yqr!19sChIJAQAAALVtbkgRgKgFrJAvzWk?authuser=0&hl=en&rclk=1",
    "rating": 3.1,
    "total_reviews": 60,
    "business_status": "OPERATIONAL",
    "opening_hours": "{}",
    "types": "Bus tour agency",
    "lat": 51.517427,
    "lng": -3.561199,
    "found_in_location": "Bridgend",
    "found_with_query": "limo wales"
  },
  {
    "name": "Pink Limos",
    "address": "Heoly Cawl Farm, Heol y cawl Farm, Tonteg, Pontypridd, CF38 1SR, GB",
    "phone": "01443 217747",
    "international_phone": "01443 217747",
    "website": "https://pinklimohire.com/",
    "google_maps_url": "https://www.google.com/maps/place/Pink+Limos/data=!4m7!3m6!1s0x486e176931068ca9:0xbeb85567e75aed0d!8m2!3d51.5780274!4d-3.3222456!16s%2Fg%2F11x9qw844!19sChIJqYwGMWkXbkgRDe1a52dVuL4?authuser=0&hl=en&rclk=1",
    "rating": 3.0,
    "total_reviews": 1,
    "business_status": "OPERATIONAL",
    "opening_hours": "{\"Friday\":[\"9\u202fam\u20139\u202fpm\"],\"Monday\":[\"9\u202fam\u20139\u202fpm\"],\"Saturday\":[\"9\u202fam\u20139\u202fpm\"],\"Sunday\":[\"9\u202fam\u20135\u202fpm\"],\"Thursday\":[\"9\u202fam\u20139\u202fpm\"],\"Tuesday\":[\"9\u202fam\u20139\u202fpm\"],\"Wednesday\":[\"9\u202fam\u20139\u202fpm\"]}",
    "types": "Limousine service",
    "lat": 51.578027,
    "lng": -3.322246,
    "found_in_location": "Pontypridd",
    "found_with_query": "limo wales"
  },
  {
    "name": "Keepings Coaches",
    "address": "Gasworks Rd, Aberdare, CF44 6RS, GB",
    "phone": "01443 478409",
    "international_phone": "01443 478409",
    "website": "http://www.keepingscoaches.co.uk/",
    "google_maps_url": "https://www.google.com/maps/place/Keepings+Coaches/data=!4m7!3m6!1s0x486e3d0f5a429081:0x87fde42aff71d493!8m2!3d51.7001507!4d-3.4218178!16s%2Fg%2F1tgfw1f6!19sChIJgZBCWg89bkgRk9Rx_yrk_Yc?authuser=0&hl=en&rclk=1",
    "rating": 2.8,
    "total_reviews": 25,
    "business_status": "OPERATIONAL",
    "opening_hours": "{\"Friday\":[\"9:30\u202fam\u20132:30\u202fpm\"],\"Monday\":[\"9:30\u202fam\u20132:30\u202fpm\"],\"Saturday\":[\"Closed\"],\"Sunday\":[\"Closed\"],\"Thursday\":[\"9:30\u202fam\u20132:30\u202fpm\"],\"Tuesday\":[\"9:30\u202fam\u20132:30\u202fpm\"],\"Wednesday\":[\"9:30\u202fam\u20132:30\u202fpm\"]}",
    "types": "Coach and minibus hire",
    "lat": 51.700151,
    "lng": -3.421818,
    "found_in_location": "Aberdare",
    "found_with_query": "limo wales"
  },
  {
    "name": "Caseyscars",
    "address": "Corporation Rd, Newport, NP19 4RD, GB",
    "phone": "07836 335665",
    "international_phone": "07836 335665",
    "website": "https://www.caseyscars.co.uk/",
    "google_maps_url": "https://www.google.com/maps/place/Caseyscars/data=!4m7!3m6!1s0x4871e7565ad5fb9d:0x52b33081636b1231!8m2!3d51.5670045!4d-2.9682943!16s%2Fg%2F11ks2njwxl!19sChIJnfvVWlbncUgRMRJrY4Ews1I?authuser=0&hl=en&rclk=1",
    "rating": 2.7,
    "total_reviews": 7,
    "business_status": "OPERATIONAL",
    "opening_hours": "{\"Friday\":[\"9\u202fam\u20135\u202fpm\"],\"Monday\":[\"9\u202fam\u20135\u202fpm\"],\"Saturday\":[\"9\u202fam\u20135\u202fpm\"],\"Sunday\":[\"9\u202fam\u20135\u202fpm\"],\"Thursday\":[\"9\u202fam\u20135\u202fpm\"],\"Tuesday\":[\"9\u202fam\u20135\u202fpm\"],\"Wednesday\":[\"9\u202fam\u20135\u202fpm\"]}",
    "types": "Limousine service",
    "lat": 51.567004,
    "lng": -2.968294,
    "found_in_location": "Newport",
    "found_with_query": "limo wales"
  },
  {
    "name": "Buddys Mini Bus Hire",
    "address": "15b Llewelyn St, Hopkinstown, Pontypridd, CF37 2RF, GB",
    "phone": "01443 400081",
    "international_phone": "01443 400081",
    "website": "https://www.buddyshire.co.uk/",
    "google_maps_url": "https://www.google.com/maps/place/Buddys+Mini+Bus+Hire/data=!4m7!3m6!1s0x486e17b258155d75:0x8886b95cc9c9ecce!8m2!3d51.6058492!4d-3.3561656!16s%2Fg%2F11bycf75zg!19sChIJdV0VWLIXbkgRzuzJyVy5hog?authuser=0&hl=en&rclk=1",
    "rating": 2.4,
    "total_reviews": 32,
    "business_status": "OPERATIONAL",
    "opening_hours": "{}",
    "types": "Coach and minibus hire",
    "lat": 51.605849,
    "lng": -3.356166,
    "found_in_location": "Pontypridd",
    "found_with_query": "limo wales"
  },
  {
    "name": "PTS Travel",
    "address": "24 Grugos Ave, Pontyberem, Llanelli, SA15 5AF, GB",
    "phone": "01269 870609",
    "international_phone": "01269 870609",
    "website": "",
    "google_maps_url": "https://www.google.com/maps/place/PTS+Travel/data=!4m7!3m6!1s0x486ee55bf794fd71:0x9c2ed4555958166b!8m2!3d51.78416!4d-4.1659415!16s%2Fg%2F1tdwv3gr!19sChIJcf2U91vlbkgRaxZYWVXULpw?authuser=0&hl=en&rclk=1",
    "rating": 2.0,
    "total_reviews": 4,
    "business_status": "OPERATIONAL",
    "opening_hours": "{\"Friday\":[\"Open 24 hours\"],\"Monday\":[\"Open 24 hours\"],\"Saturday\":[\"Open 24 hours\"],\"Sunday\":[\"Open 24 hours\"],\"Thursday\":[\"Open 24 hours\"],\"Tuesday\":[\"Open 24 hours\"],\"Wednesday\":[\"Open 24 hours\"]}",
    "types": "Coach and minibus hire",
    "lat": 51.78416,
    "lng": -4.165941,
    "found_in_location": "Llanelli",
    "found_with_query": "limo wales"
  },
  {
    "name": "Swansea Limousine Hire",
    "address": "West Glamorgan House, 12 Orchard St, Swansea, SA1 5AD, GB",
    "phone": "01792 775871",
    "international_phone": "01792 775871",
    "website": "http://www.swansealimos.co.uk/",
    "google_maps_url": "https://www.google.com/maps/place/Swansea+Limousine+Hire/data=!4m7!3m6!1s0x486ef54a05a1046b:0xfea894484088fa4a!8m2!3d51.6219339!4d-3.9428815!16s%2Fg%2F1yh9v0383!19sChIJawShBUr1bkgRSvqIQEiUqP4?authuser=0&hl=en&rclk=1",
    "rating": 1.0,
    "total_reviews": 1,
    "business_status": "OPERATIONAL",
    "opening_hours": "{}",
    "types": "Limousine service",
    "lat": 51.621934,
    "lng": -3.942881,
    "found_in_location": "Swansea",
    "found_with_query": "limo wales"
  },
  {
    "name": "Unicorn Travel Wrexham Limited",
    "address": "10 Fairfield, Brymbo, Wrexham, LL11 5ED, GB",
    "phone": "01978 856048",
    "international_phone": "01978 856048",
    "website": "https://www.unicorntravelwrexham.co.uk/",
    "google_maps_url": "https://www.google.com/maps/place/Unicorn+Travel+Wrexham+Limited/data=!4m7!3m6!1s0x487ac74fd0d048e9:0x68c57ff7bca0c316!8m2!3d53.0768689!4d-3.0503355!16s%2Fg%2F11h63vyh4k!19sChIJ6UjQ0E_HekgRFsOgvPd_xWg?authuser=0&hl=en&rclk=1",
    "rating": 0.0,
    "total_reviews": 0,
    "business_status": "OPERATIONAL",
    "opening_hours": "{\"Friday\":[\"8\u202fam\u20135:30\u202fpm\"],\"Monday\":[\"8\u202fam\u20135:30\u202fpm\"],\"Saturday\":[\"8\u202fam\u201312:30\u202fpm\"],\"Sunday\":[\"Closed\"],\"Thursday\":[\"8\u202fam\u20135:30\u202fpm\"],\"Tuesday\":[\"8\u202fam\u20135:30\u202fpm\"],\"Wednesday\":[\"8\u202fam\u20135:30\u202fpm\"]}",
    "types": "Coach and minibus hire",
    "lat": 53.076869,
    "lng": -3.050335,
    "found_in_location": "Wrexham",
    "found_with_query": "limo wales"
  },
  {
    "name": "Wrexham Minibus Co",
    "address": "Aberderfyn Rd, Ponciau, Wrexham, LL14 1SP, GB",
    "phone": "01978 843355",
    "international_phone": "01978 843355",
    "website": "https://www.wrexhamminibus.co.uk/",
    "google_maps_url": "https://www.google.com/maps/place/Wrexham+Minibus+Co/data=!4m7!3m6!1s0x487ab7fb01aee4b3:0xc2ca476e322f39be!8m2!3d53.0113818!4d-3.0468382!16s%2Fg%2F11f3_zw96v!19sChIJs-SuAfu3ekgRvjkvMm5HysI?authuser=0&hl=en&rclk=1",
    "rating": 0.0,
    "total_reviews": 0,
    "business_status": "OPERATIONAL",
    "opening_hours": "{}",
    "types": "Bus charter",
    "lat": 53.011382,
    "lng": -3.046838,
    "found_in_location": "Wrexham",
    "found_with_query": "limo wales"
  },
  {
    "name": "R.B Wedding Cars",
    "address": "Hermitage Park, 3 Avalon Ct, Wrexham, LL13 7GX, GB",
    "phone": "07783 074320",
    "international_phone": "07783 074320",
    "website": "",
    "google_maps_url": "https://www.google.com/maps/place/R.B+Wedding+Cars/data=!4m7!3m6!1s0x487ac7141b71a281:0xdcd81ac8683348d8!8m2!3d53.03496!4d-2.9893987!16s%2Fg%2F1tg5bn44!19sChIJgaJxGxTHekgR2EgzaMga2Nw?authuser=0&hl=en&rclk=1",
    "rating": 0.0,
    "total_reviews": 0,
    "business_status": "OPERATIONAL",
    "opening_hours": "{\"Friday\":[\"9\u202fam\u20138\u202fpm\"],\"Monday\":[\"9\u202fam\u20138\u202fpm\"],\"Saturday\":[\"10\u202fam\u20138\u202fpm\"],\"Sunday\":[\"10\u202fam\u20138\u202fpm\"],\"Thursday\":[\"9\u202fam\u20138\u202fpm\"],\"Tuesday\":[\"9\u202fam\u20138\u202fpm\"],\"Wednesday\":[\"9\u202fam\u20138\u202fpm\"]}",
    "types": "Limousine service",
    "lat": 53.03496,
    "lng": -2.989399,
    "found_in_location": "Wrexham",
    "found_with_query": "limo wales"
  },
  {
    "name": "Newport Hummer",
    "address": "182 Maesglas Cres, Newport, NP2 0 3DB, GB",
    "phone": "01633 746578",
    "international_phone": "01633 746578",
    "website": "",
    "google_maps_url": "https://www.google.com/maps/place/Newport+Hummer/data=!4m7!3m6!1s0x4871e150f857f587:0x68b65f09f2b4878e!8m2!3d51.5683304!4d-3.0141624!16s%2Fg%2F11jh76_tg9!19sChIJh_VX-FDhcUgRjoe08glftmg?authuser=0&hl=en&rclk=1",
    "rating": 0.0,
    "total_reviews": 0,
    "business_status": "OPERATIONAL",
    "opening_hours": "{}",
    "types": "Limousine service",
    "lat": 51.56833,
    "lng": -3.014162,
    "found_in_location": "Newport",
    "found_with_query": "limo wales"
  },
  {
    "name": "Dreamland Limos",
    "address": "10 Ainon Rd, Bangor, LL57 2YD, GB",
    "phone": "01248 372372",
    "international_phone": "01248 372372",
    "website": "",
    "google_maps_url": "https://www.google.com/maps/place/Dreamland+Limos/data=!4m7!3m6!1s0x4865075b042c4335:0xf9d79a414ae10d6!8m2!3d53.2184232!4d-4.1402897!16s%2Fg%2F1vp6zlt6!19sChIJNUMsBFsHZUgR1hCuFKR5nQ8?authuser=0&hl=en&rclk=1",
    "rating": 0.0,
    "total_reviews": 0,
    "business_status": "OPERATIONAL",
    "opening_hours": "{}",
    "types": "Limousine service",
    "lat": 53.218423,
    "lng": -4.14029,
    "found_in_location": "Bangor",
    "found_with_query": "limo wales"
  },
  {
    "name": "The Private Driver",
    "address": "Sovereign Quay, 2 Havannah St, Cardiff, CF10 5SF, GB",
    "phone": "07523 342911",
    "international_phone": "07523 342911",
    "website": "",
    "google_maps_url": "https://www.google.com/maps/place/The+Private+Driver/data=!4m7!3m6!1s0x486e03e37da8d91b:0xaa2032180b5a3803!8m2!3d51.4617413!4d-3.1678747!16s%2Fg%2F11lp7ms7yd!19sChIJG9mofeMDbkgRAzhaCxgyIKo?authuser=0&hl=en&rclk=1",
    "rating": 0.0,
    "total_reviews": 0,
    "business_status": "OPERATIONAL",
    "opening_hours": "{\"Friday\":[\"Open 24 hours\"],\"Monday\":[\"Open 24 hours\"],\"Saturday\":[\"Open 24 hours\"],\"Sunday\":[\"Open 24 hours\"],\"Thursday\":[\"Open 24 hours\"],\"Tuesday\":[\"Open 24 hours\"],\"Wednesday\":[\"Open 24 hours\"]}",
    "types": "Chauffeur service",
    "lat": 51.461741,
    "lng": -3.167875,
    "found_in_location": "Cardiff",
    "found_with_query": "limo wales"
  },
  {
    "name": "Cardiff and Bristol Limo Hire",
    "address": "Severn Bridge Industrial Estate, 50a Symondscliff Way, Portskewett, Caldicot, Caldicot, NP26 5PW, GB",
    "phone": "0800 180 4305",
    "international_phone": "0800 180 4305",
    "website": "http://cardiffandbristollimohire.com/",
    "google_maps_url": "https://www.google.com/maps/place/Cardiff+and+Bristol+Limo+Hire/data=!4m7!3m6!1s0x4871eb6b5bffffff:0x52d94896253392dd!8m2!3d51.5861849!4d-2.737894!16s%2Fg%2F11c7sqwrjw!19sChIJ____W2vrcUgR3ZIzJZZI2VI?authuser=0&hl=en&rclk=1",
    "rating": 0.0,
    "total_reviews": 0,
    "business_status": "OPERATIONAL",
    "opening_hours": "{\"Friday\":[\"10\u202fam\u20135\u202fpm\"],\"Monday\":[\"10\u202fam\u20135\u202fpm\"],\"Saturday\":[\"10\u202fam\u20135\u202fpm\"],\"Sunday\":[\"10\u202fam\u20135\u202fpm\"],\"Thursday\":[\"10\u202fam\u20135\u202fpm\"],\"Tuesday\":[\"10\u202fam\u20135\u202fpm\"],\"Wednesday\":[\"10\u202fam\u20135\u202fpm\"]}",
    "types": "Car rental company",
    "lat": 51.586185,
    "lng": -2.737894,
    "found_in_location": "Caldicot",
    "found_with_query": "limo wales"
  },
  {
    "name": "Island Limousine Ltd",
    "address": "Spithead Business Centre, Newport Rd, Sandown, PO36 9PH, GB",
    "phone": "01983 407373",
    "international_phone": "01983 407373",
    "website": "",
    "google_maps_url": "https://www.google.com/maps/place/Island+Limousine+Ltd/data=!4m7!3m6!1s0x48748a3bcb7abc3b:0x81d4d26ac3289a54!8m2!3d50.6449988!4d-1.1813525!16s%2Fg%2F1tgfplg8!19sChIJO7x6yzuKdEgRVJoow2rS1IE?authuser=0&hl=en&rclk=1",
    "rating": 0.0,
    "total_reviews": 0,
    "business_status": "OPERATIONAL",
    "opening_hours": "{}",
    "types": "Limousine service",
    "lat": 50.644999,
    "lng": -1.181353,
    "found_in_location": "Sandown",
    "found_with_query": "limo wales"
  },
  {
    "name": "Lady Tiara Wedding Cars",
    "address": "New Premier Buildings, Newport Rd, Bedwas, Caerphilly, CF83 8YE, GB",
    "phone": "07808 700007",
    "international_phone": "07808 700007",
    "website": "",
    "google_maps_url": "https://www.google.com/maps/place/Lady+Tiara+Wedding+Cars/data=!4m7!3m6!1s0x486e1edb0b794c7d:0x40c48f10ed1d24ea!8m2!3d51.5898362!4d-3.1897247!16s%2Fg%2F1pp2wyl0d!19sChIJfUx5C9sebkgR6iQd7RCPxEA?authuser=0&hl=en&rclk=1",
    "rating": 0.0,
    "total_reviews": 0,
    "business_status": "OPERATIONAL",
    "opening_hours": "{}",
    "types": "Limousine service",
    "lat": 51.589836,
    "lng": -3.189725,
    "found_in_location": "Caerphilly",
    "found_with_query": "limo wales"
  },
  {
    "name": "G T Mini Bus Hire",
    "address": "15 Pen Llwyn, Bridgend, CF31 5AZ, GB",
    "phone": "01656 652362",
    "international_phone": "01656 652362",
    "website": "",
    "google_maps_url": "https://www.google.com/maps/place/G+T+Mini+Bus+Hire/data=!4m7!3m6!1s0x486e6c2ccbd1be8f:0x938d8bc7ab03644c!8m2!3d51.5025439!4d-3.5902082!16s%2Fg%2F11c54b28_p!19sChIJj77RyyxsbkgRTGQDq8eLjZM?authuser=0&hl=en&rclk=1",
    "rating": 0.0,
    "total_reviews": 0,
    "business_status": "OPERATIONAL",
    "opening_hours": "{}",
    "types": "Taxi service",
    "lat": 51.502544,
    "lng": -3.590208,
    "found_in_location": "Bridgend",
    "found_with_query": "limo wales"
  },
  {
    "name": "Grove Wedding Services",
    "address": "Mayals Rd, Mayals, Swansea, SA3 5HQ, GB",
    "phone": "07725 912022",
    "international_phone": "07725 912022",
    "website": "http://www.groveweddingservices.co.uk/",
    "google_maps_url": "https://www.google.com/maps/place/Grove+Wedding+Services/data=!4m7!3m6!1s0x486e8bca3863abff:0x36e17169b34c424f!8m2!3d51.5920517!4d-4.0129922!16s%2Fg%2F11g0qqk6qz!19sChIJ_6tjOMqLbkgRT0JMs2lx4TY?authuser=0&hl=en&rclk=1",
    "rating": 0.0,
    "total_reviews": 0,
    "business_status": "OPERATIONAL",
    "opening_hours": "{\"Friday\":[\"Open 24 hours\"],\"Monday\":[\"Open 24 hours\"],\"Saturday\":[\"Open 24 hours\"],\"Sunday\":[\"Open 24 hours\"],\"Thursday\":[\"Open 24 hours\"],\"Tuesday\":[\"Open 24 hours\"],\"Wednesday\":[\"Open 24 hours\"]}",
    "types": "Wedding service",
    "lat": 51.592052,
    "lng": -4.012992,
    "found_in_location": "Swansea",
    "found_with_query": "limo wales"
  },
  {
    "name": "HAPPILY EVER AFTER WEDDING CARS",
    "address": "The Coppings, Bryncethin, Bridgend, CF32 9YR, GB",
    "phone": "01656 260456",
    "international_phone": "01656 260456",
    "website": "http://happilyeverafterweddingcars.co.uk/",
    "google_maps_url": "https://www.google.com/maps/place/HAPPILY+EVER+AFTER+WEDDING+CARS/data=!4m7!3m6!1s0x486e6b880510fd09:0x2978639e8e61a53d!8m2!3d51.545621!4d-3.566694!16s%2Fg%2F11ld230qkx!19sChIJCf0QBYhrbkgRPaVhjp5jeCk?authuser=0&hl=en&rclk=1",
    "rating": 0.0,
    "total_reviews": 0,
    "business_status": "OPERATIONAL",
    "opening_hours": "{\"Friday\":[\"9\u202fam\u20135\u202fpm\"],\"Monday\":[\"9\u202fam\u20135\u202fpm\"],\"Saturday\":[\"Closed\"],\"Sunday\":[\"Closed\"],\"Thursday\":[\"9\u202fam\u20135\u202fpm\"],\"Tuesday\":[\"9\u202fam\u20135\u202fpm\"],\"Wednesday\":[\"9\u202fam\u20135\u202fpm\"]}",
    "types": "Car rental company",
    "lat": 51.545621,
    "lng": -3.566694,
    "found_in_location": "Bridgend",
    "found_with_query": "limo wales"
  },
  {
    "name": "Fairytale Carriages wedding cars",
    "address": "Pontcynon Ind Est, Abercynon, Mountain Ash, CF45 4EP, GB",
    "phone": "07756 046640",
    "international_phone": "07756 046640",
    "website": "http://fairytaleweddingcarhire.co.uk/",
    "google_maps_url": "https://www.google.com/maps/place/Fairytale+Carriages+wedding+cars/data=!4m7!3m6!1s0x486e3d40f708450b:0x126a1e8b6aa0fecf!8m2!3d51.6553541!4d-3.3368239!16s%2Fg%2F11y6kfwd8j!19sChIJC0UI90A9bkgRz_6gaoseahI?authuser=0&hl=en&rclk=1",
    "rating": 0.0,
    "total_reviews": 0,
    "business_status": "OPERATIONAL",
    "opening_hours": "{\"Friday\":[\"8\u202fam\u20134:30\u202fpm\"],\"Monday\":[\"8\u202fam\u20134:30\u202fpm\"],\"Saturday\":[\"8\u202fam\u201311\u202fpm\"],\"Sunday\":[\"Closed\"],\"Thursday\":[\"8\u202fam\u20134:30\u202fpm\"],\"Tuesday\":[\"8\u202fam\u20134:30\u202fpm\"],\"Wednesday\":[\"8\u202fam\u20134:30\u202fpm\"]}",
    "types": "Wedding service",
    "lat": 51.655354,
    "lng": -3.336824,
    "found_in_location": "Mountain Ash",
    "found_with_query": "limo wales"
  }
]